<?xml version="1.0" encoding="utf-8"?><soap:Envelope xmlns:soap="http://schemas.xmlsoap.org/soap/envelope/" xmlns:xsi="http://www.w3.org/2001/XMLSchema-instance" xmlns:xsd="http://www.w3.org/2001/XMLSchema"><soap:Body><GetHotelSearchListForCustomerCountResponse xmlns="http://www.rts.co.kr/"><GetHotelSearchListForCustomerCountResult><GetHotelSearchListResponse><GetHotelSearchListResult><LanguageCode>AR</LanguageCode><LanguageName><![CDATA[Argentina]]></LanguageName><NationalityCode>EU</NationalityCode><NationalityName><![CDATA[유럽인]]></NationalityName><ContinentCode>A</ContinentCode><CityCode>SEL</CityCode><CityEname><![CDATA[Seoul]]></CityEname><CityName><![CDATA[Seul]]></CityName><CountryCode>KR</CountryCode><CountryEname><![CDATA[Korea]]></CountryEname><CountryName><![CDATA[Corea]]></CountryName><StateCode>A1</StateCode><StateEname><![CDATA[-]]></StateEname><StateName><![CDATA[-]]></StateName><CheckInDate>2020-04-11</CheckInDate><CheckInWeekday>SAT</CheckInWeekday><CheckOutDate>2020-04-14</CheckOutDate><CheckOutWeekday>TUE</CheckOutWeekday><Duration>3</Duration><CheckInLeftDays></CheckInLeftDays><ItemName><![CDATA[]]></ItemName><ItemCode></ItemCode><ItemNo>0</ItemNo><StarRating>0</StarRating><LocationCode></LocationCode><AvailableHotelOnly>True</AvailableHotelOnly><RecommendHotelOnly>False</RecommendHotelOnly><TotalResultCount>9</TotalResultCount><ExchangeConvertDate>2011-03-18</ExchangeConvertDate><SellingCurrencyCode>USD</SellingCurrencyCode><ClientCurrencyCode>USD</ClientCurrencyCode><SellingConvertRate>1146.210000</SellingConvertRate><CityEventList></CityEventList><RoomList><RoomInfo><BedTypeCode>BED01</BedTypeCode><RoomCount>3</RoomCount><ChlidAge1>0</ChlidAge1><ChlidAge2>0</ChlidAge2></RoomInfo></RoomList><HotelSearchList><HotelItemInfo><ItemCode>SEL0037</ItemCode><ItemName><![CDATA[mayfield hotel]]></ItemName><StarRating>5</StarRating><RecommendYn>False</RecommendYn><ExpertReportYn>False</ExpertReportYn><FirstImageFileName></FirstImageFileName><HotelDescription><![CDATA[]]></HotelDescription><BackpackYn>False</BackpackYn><BusinessYn>False</BusinessYn><HoneymoonYn>False</HoneymoonYn><FairYn>False</FairYn><AirPackYn>False</AirPackYn><BookingCount>1</BookingCount><LocationList></LocationList><PriceList><PriceInfo><ItemNo>21</ItemNo><ItemCode>SEL0037</ItemCode><SupplierCompCode></SupplierCompCode><RoomTypeCode>42976|BQERAT|BNRZD|Q|E|Standard Twin|e15158f5-a256-1281-c5f6-c9597ea10d95|NONE|BGKRDDDD|~None</RoomTypeCode><RoomTypeName><![CDATA[Standard Twin]]></RoomTypeName><BreakfastTypeName><![CDATA[None]]></BreakfastTypeName><AddBreakfastTypeName></AddBreakfastTypeName><PriceComment><![CDATA[]]></PriceComment><FareRateType>None</FareRateType><PriceStatus>Available</PriceStatus><NetCurrencyCode>USD</NetCurrencyCode><NetConvertRate>1.00000000</NetConvertRate><SellerNetPrice>875</SellerNetPrice><LocalNetPrice>875.44</LocalNetPrice><SellerMarkupPrice>0</SellerMarkupPrice><RecommendClientPrice>980</RecommendClientPrice><SellerClientPrice>875</SellerClientPrice><Comment><![CDATA[]]></Comment><DoubleBedYn>false</DoubleBedYn><SupplierPromotion><PromotionName><![CDATA[Long Stay Deal. Price includes 28% discount!]]></PromotionName><PromotionDescription><![CDATA[]]></PromotionDescription></SupplierPromotion></PriceInfo><PriceInfo><ItemNo>21</ItemNo><ItemCode>SEL0037</ItemCode><SupplierCompCode></SupplierCompCode><RoomTypeCode>42976|BQERAT|BNRZD|Q|E|Standard Double|c1150cd1-8acc-4d2c-f863-c05e8ad9e2d5|NONE|BGKRDDDD|~None</RoomTypeCode><RoomTypeName><![CDATA[Standard Double]]></RoomTypeName><BreakfastTypeName><![CDATA[None]]></BreakfastTypeName><AddBreakfastTypeName></AddBreakfastTypeName><PriceComment><![CDATA[]]></PriceComment><FareRateType>None</FareRateType><PriceStatus>Available</PriceStatus><NetCurrencyCode>USD</NetCurrencyCode><NetConvertRate>1.00000000</NetConvertRate><SellerNetPrice>875</SellerNetPrice><LocalNetPrice>875.44</LocalNetPrice><SellerMarkupPrice>0</SellerMarkupPrice><RecommendClientPrice>980</RecommendClientPrice><SellerClientPrice>875</SellerClientPrice><Comment><![CDATA[]]></Comment><DoubleBedYn>false</DoubleBedYn><SupplierPromotion><PromotionName><![CDATA[Long Stay Deal. Price includes 28% discount!]]></PromotionName><PromotionDescription><![CDATA[]]></PromotionDescription></SupplierPromotion></PriceInfo><PriceInfo><ItemNo>21</ItemNo><ItemCode>SEL0037</ItemCode><SupplierCompCode></SupplierCompCode><RoomTypeCode>42976|NGCRGB|AQBRDZ|Q|E|Standard Twin|b956fd5f-3b99-2224-f3be-b910b053348d|NONE|HFMJRMFFZ|~Breakfast</RoomTypeCode><RoomTypeName><![CDATA[Standard Twin]]></RoomTypeName><BreakfastTypeName><![CDATA[Breakfast]]></BreakfastTypeName><AddBreakfastTypeName></AddBreakfastTypeName><PriceComment><![CDATA[]]></PriceComment><FareRateType>None</FareRateType><PriceStatus>Available</PriceStatus><NetCurrencyCode>USD</NetCurrencyCode><NetConvertRate>1.00000000</NetConvertRate><SellerNetPrice>1064</SellerNetPrice><LocalNetPrice>1063.60</LocalNetPrice><SellerMarkupPrice>0</SellerMarkupPrice><RecommendClientPrice>1190</RecommendClientPrice><SellerClientPrice>1064</SellerClientPrice><Comment><![CDATA[]]></Comment><DoubleBedYn>false</DoubleBedYn><SupplierPromotion><PromotionName><![CDATA[Long Stay Deal. Price includes 28% discount!]]></PromotionName><PromotionDescription><![CDATA[]]></PromotionDescription></SupplierPromotion></PriceInfo><PriceInfo><ItemNo>21</ItemNo><ItemCode>SEL0037</ItemCode><SupplierCompCode></SupplierCompCode><RoomTypeCode>42976|NGCRGB|AQBRDZ|Q|E|Standard Double|26099481-cefd-c29c-505b-deceb5454ae7|NONE|HFMJRMFFZ|~Breakfast</RoomTypeCode><RoomTypeName><![CDATA[Standard Double]]></RoomTypeName><BreakfastTypeName><![CDATA[Breakfast]]></BreakfastTypeName><AddBreakfastTypeName></AddBreakfastTypeName><PriceComment><![CDATA[]]></PriceComment><FareRateType>None</FareRateType><PriceStatus>Available</PriceStatus><NetCurrencyCode>USD</NetCurrencyCode><NetConvertRate>1.00000000</NetConvertRate><SellerNetPrice>1064</SellerNetPrice><LocalNetPrice>1063.60</LocalNetPrice><SellerMarkupPrice>0</SellerMarkupPrice><RecommendClientPrice>1190</RecommendClientPrice><SellerClientPrice>1064</SellerClientPrice><Comment><![CDATA[]]></Comment><DoubleBedYn>false</DoubleBedYn><SupplierPromotion><PromotionName><![CDATA[Long Stay Deal. Price includes 28% discount!]]></PromotionName><PromotionDescription><![CDATA[]]></PromotionDescription></SupplierPromotion></PriceInfo><PriceInfo><ItemNo>21</ItemNo><ItemCode>SEL0037</ItemCode><SupplierCompCode></SupplierCompCode><RoomTypeCode>42976|AAQCRTC|AZZRBC|Q|E|Studio Suite|38296a55-b9a5-535f-2f39-c6f42ad59e0f|NONE|HZFKRHKBK|~None</RoomTypeCode><RoomTypeName><![CDATA[Studio Suite]]></RoomTypeName><BreakfastTypeName><![CDATA[None]]></BreakfastTypeName><AddBreakfastTypeName></AddBreakfastTypeName><PriceComment><![CDATA[]]></PriceComment><FareRateType>None</FareRateType><PriceStatus>Available</PriceStatus><NetCurrencyCode>USD</NetCurrencyCode><NetConvertRate>1.00000000</NetConvertRate><SellerNetPrice>1205</SellerNetPrice><LocalNetPrice>1205.16</LocalNetPrice><SellerMarkupPrice>0</SellerMarkupPrice><RecommendClientPrice>1349</RecommendClientPrice><SellerClientPrice>1205</SellerClientPrice><Comment><![CDATA[]]></Comment><DoubleBedYn>false</DoubleBedYn><SupplierPromotion><PromotionName><![CDATA[Long Stay Deal. Price includes 28% discount!]]></PromotionName><PromotionDescription><![CDATA[]]></PromotionDescription></SupplierPromotion></PriceInfo><PriceInfo><ItemNo>21</ItemNo><ItemCode>SEL0037</ItemCode><SupplierCompCode></SupplierCompCode><RoomTypeCode>42976|AZGBRZG|ADZRQE|Q|E|Studio Suite|650a8661-74a0-848c-a461-d750ba6d4450|NONE|HJPJRJHDJ|~Breakfast</RoomTypeCode><RoomTypeName><![CDATA[Studio Suite]]></RoomTypeName><BreakfastTypeName><![CDATA[Breakfast]]></BreakfastTypeName><AddBreakfastTypeName></AddBreakfastTypeName><PriceComment><![CDATA[]]></PriceComment><FareRateType>None</FareRateType><PriceStatus>Available</PriceStatus><NetCurrencyCode>USD</NetCurrencyCode><NetConvertRate>1.00000000</NetConvertRate><SellerNetPrice>1393</SellerNetPrice><LocalNetPrice>1393.31</LocalNetPrice><SellerMarkupPrice>0</SellerMarkupPrice><RecommendClientPrice>1559</RecommendClientPrice><SellerClientPrice>1393</SellerClientPrice><Comment><![CDATA[]]></Comment><DoubleBedYn>false</DoubleBedYn><SupplierPromotion><PromotionName><![CDATA[Long Stay Deal. Price includes 28% discount!]]></PromotionName><PromotionDescription><![CDATA[]]></PromotionDescription></SupplierPromotion></PriceInfo></PriceList></HotelItemInfo><HotelItemInfo><ItemCode>SEL0043</ItemCode><ItemName><![CDATA[president hotel]]></ItemName><StarRating>4</StarRating><RecommendYn>True</RecommendYn><ExpertReportYn>False</ExpertReportYn><FirstImageFileName></FirstImageFileName><HotelDescription><![CDATA[]]></HotelDescription><BackpackYn>True</BackpackYn><BusinessYn>True</BusinessYn><HoneymoonYn>False</HoneymoonYn><FairYn>False</FairYn><AirPackYn>False</AirPackYn><BookingCount>1</BookingCount><GeoCode><Latitude>37.565688</Latitude><Longitude>126.979305</Longitude></GeoCode><LocationList></LocationList><PriceList><PriceInfo><ItemNo>29</ItemNo><ItemCode>SEL0043</ItemCode><SupplierCompCode></SupplierCompCode><RoomTypeCode>43154|AQAERTG|AAZRTE|Q|E|Standard Double|958a51c0-f9c5-21e1-cfa3-b18fe08a6fac|NONE|HHFDRPFFJ|~None</RoomTypeCode><RoomTypeName><![CDATA[Standard Double]]></RoomTypeName><BreakfastTypeName><![CDATA[None]]></BreakfastTypeName><AddBreakfastTypeName></AddBreakfastTypeName><PriceComment><![CDATA[]]></PriceComment><FareRateType>None</FareRateType><PriceStatus>Available</PriceStatus><NetCurrencyCode>USD</NetCurrencyCode><NetConvertRate>1.00000000</NetConvertRate><SellerNetPrice>1105</SellerNetPrice><LocalNetPrice>1104.90</LocalNetPrice><SellerMarkupPrice>0</SellerMarkupPrice><RecommendClientPrice>1237</RecommendClientPrice><SellerClientPrice>1105</SellerClientPrice><Comment><![CDATA[]]></Comment><DoubleBedYn>false</DoubleBedYn><SupplierPromotion><PromotionName><![CDATA[Long Stay Deal. Price includes 22% discount!]]></PromotionName><PromotionDescription><![CDATA[]]></PromotionDescription></SupplierPromotion></PriceInfo><PriceInfo><ItemNo>29</ItemNo><ItemCode>SEL0043</ItemCode><SupplierCompCode></SupplierCompCode><RoomTypeCode>43154|AQAERTG|AAZRTE|Q|E|Standard Twin|856456e4-5d9b-58a2-de01-5527dbf7d134|NONE|HHFDRPFFJ|~None</RoomTypeCode><RoomTypeName><![CDATA[Standard Twin]]></RoomTypeName><BreakfastTypeName><![CDATA[None]]></BreakfastTypeName><AddBreakfastTypeName></AddBreakfastTypeName><PriceComment><![CDATA[]]></PriceComment><FareRateType>None</FareRateType><PriceStatus>Available</PriceStatus><NetCurrencyCode>USD</NetCurrencyCode><NetConvertRate>1.00000000</NetConvertRate><SellerNetPrice>1105</SellerNetPrice><LocalNetPrice>1104.90</LocalNetPrice><SellerMarkupPrice>0</SellerMarkupPrice><RecommendClientPrice>1237</RecommendClientPrice><SellerClientPrice>1105</SellerClientPrice><Comment><![CDATA[]]></Comment><DoubleBedYn>false</DoubleBedYn><SupplierPromotion><PromotionName><![CDATA[Long Stay Deal. Price includes 22% discount!]]></PromotionName><PromotionDescription><![CDATA[]]></PromotionDescription></SupplierPromotion></PriceInfo><PriceInfo><ItemNo>29</ItemNo><ItemCode>SEL0043</ItemCode><SupplierCompCode></SupplierCompCode><RoomTypeCode>43154|AATQRAN|AZBRNA|Q|E|Deluxe Twin|1f0464bc-24a1-3697-3c39-c878563a8e12|NONE|HZMDRMFGH|~None</RoomTypeCode><RoomTypeName><![CDATA[Deluxe Twin]]></RoomTypeName><BreakfastTypeName><![CDATA[None]]></BreakfastTypeName><AddBreakfastTypeName></AddBreakfastTypeName><PriceComment><![CDATA[]]></PriceComment><FareRateType>None</FareRateType><PriceStatus>Available</PriceStatus><NetCurrencyCode>USD</NetCurrencyCode><NetConvertRate>1.00000000</NetConvertRate><SellerNetPrice>1265</SellerNetPrice><LocalNetPrice>1264.61</LocalNetPrice><SellerMarkupPrice>0</SellerMarkupPrice><RecommendClientPrice>1415</RecommendClientPrice><SellerClientPrice>1265</SellerClientPrice><Comment><![CDATA[]]></Comment><DoubleBedYn>false</DoubleBedYn><SupplierPromotion><PromotionName><![CDATA[Long Stay Deal. Price includes 22% discount!]]></PromotionName><PromotionDescription><![CDATA[]]></PromotionDescription></SupplierPromotion></PriceInfo><PriceInfo><ItemNo>29</ItemNo><ItemCode>SEL0043</ItemCode><SupplierCompCode></SupplierCompCode><RoomTypeCode>43154|AATQRAN|AZBRNA|Q|E|Deluxe Double|23d9343f-d3a6-99d0-05f5-b56a94812156|NONE|HZMDRMFGH|~None</RoomTypeCode><RoomTypeName><![CDATA[Deluxe Double]]></RoomTypeName><BreakfastTypeName><![CDATA[None]]></BreakfastTypeName><AddBreakfastTypeName></AddBreakfastTypeName><PriceComment><![CDATA[]]></PriceComment><FareRateType>None</FareRateType><PriceStatus>Available</PriceStatus><NetCurrencyCode>USD</NetCurrencyCode><NetConvertRate>1.00000000</NetConvertRate><SellerNetPrice>1265</SellerNetPrice><LocalNetPrice>1264.61</LocalNetPrice><SellerMarkupPrice>0</SellerMarkupPrice><RecommendClientPrice>1415</RecommendClientPrice><SellerClientPrice>1265</SellerClientPrice><Comment><![CDATA[]]></Comment><DoubleBedYn>false</DoubleBedYn><SupplierPromotion><PromotionName><![CDATA[Long Stay Deal. Price includes 22% discount!]]></PromotionName><PromotionDescription><![CDATA[]]></PromotionDescription></SupplierPromotion></PriceInfo><PriceInfo><ItemNo>29</ItemNo><ItemCode>SEL0043</ItemCode><SupplierCompCode></SupplierCompCode><RoomTypeCode>43154|AZTCRDN|ADQRTA|Q|E|Corner Single Room|8289e1f5-8861-8ded-4a10-fa02f41a37e5|NONE|HJGPRJBDH|~None</RoomTypeCode><RoomTypeName><![CDATA[Corner Single Room]]></RoomTypeName><BreakfastTypeName><![CDATA[None]]></BreakfastTypeName><AddBreakfastTypeName></AddBreakfastTypeName><PriceComment><![CDATA[]]></PriceComment><FareRateType>None</FareRateType><PriceStatus>Available</PriceStatus><NetCurrencyCode>USD</NetCurrencyCode><NetConvertRate>1.00000000</NetConvertRate><SellerNetPrice>1379</SellerNetPrice><LocalNetPrice>1379.38</LocalNetPrice><SellerMarkupPrice>0</SellerMarkupPrice><RecommendClientPrice>1544</RecommendClientPrice><SellerClientPrice>1379</SellerClientPrice><Comment><![CDATA[]]></Comment><DoubleBedYn>false</DoubleBedYn></PriceInfo><PriceInfo><ItemNo>29</ItemNo><ItemCode>SEL0043</ItemCode><SupplierCompCode></SupplierCompCode><RoomTypeCode>43154|AETCRZA|ACARTN|Q|E|Triple|f5e1d283-73f9-ac6d-1607-5881701f9d68|NONE|HDBBRFGBP|~None</RoomTypeCode><RoomTypeName><![CDATA[Triple]]></RoomTypeName><BreakfastTypeName><![CDATA[None]]></BreakfastTypeName><AddBreakfastTypeName></AddBreakfastTypeName><PriceComment><![CDATA[]]></PriceComment><FareRateType>None</FareRateType><PriceStatus>Available</PriceStatus><NetCurrencyCode>USD</NetCurrencyCode><NetConvertRate>1.00000000</NetConvertRate><SellerNetPrice>1488</SellerNetPrice><LocalNetPrice>1488.08</LocalNetPrice><SellerMarkupPrice>0</SellerMarkupPrice><RecommendClientPrice>1666</RecommendClientPrice><SellerClientPrice>1488</SellerClientPrice><Comment><![CDATA[]]></Comment><DoubleBedYn>false</DoubleBedYn><SupplierPromotion><PromotionName><![CDATA[Long Stay Deal. Price includes 22% discount!]]></PromotionName><PromotionDescription><![CDATA[]]></PromotionDescription></SupplierPromotion></PriceInfo></PriceList></HotelItemInfo><HotelItemInfo><ItemCode>SEL0048</ItemCode><ItemName><![CDATA[riviera hotel]]></ItemName><StarRating>4</StarRating><RecommendYn>False</RecommendYn><ExpertReportYn>False</ExpertReportYn><FirstImageFileName></FirstImageFileName><HotelDescription><![CDATA[]]></HotelDescription><BackpackYn>False</BackpackYn><BusinessYn>False</BusinessYn><HoneymoonYn>False</HoneymoonYn><FairYn>False</FairYn><AirPackYn>False</AirPackYn><BookingCount>2</BookingCount><GeoCode><Latitude>37.523835</Latitude><Longitude>127.054181</Longitude></GeoCode><LocationList></LocationList><PriceList><PriceInfo><ItemNo>36</ItemNo><ItemCode>SEL0048</ItemCode><SupplierCompCode></SupplierCompCode><RoomTypeCode>9364|NDNRZE|AQCRDG|Q|E|Deluxe Twin|cdfddbdb-78ab-0254-f039-437873c42507|NONE|HFJDRMMFG|~None</RoomTypeCode><RoomTypeName><![CDATA[Deluxe Twin]]></RoomTypeName><BreakfastTypeName><![CDATA[None]]></BreakfastTypeName><AddBreakfastTypeName></AddBreakfastTypeName><PriceComment><![CDATA[]]></PriceComment><FareRateType>None</FareRateType><PriceStatus>Available</PriceStatus><NetCurrencyCode>USD</NetCurrencyCode><NetConvertRate>1.00000000</NetConvertRate><SellerNetPrice>1035</SellerNetPrice><LocalNetPrice>1034.66</LocalNetPrice><SellerMarkupPrice>0</SellerMarkupPrice><RecommendClientPrice>1158</RecommendClientPrice><SellerClientPrice>1035</SellerClientPrice><Comment><![CDATA[]]></Comment><DoubleBedYn>false</DoubleBedYn></PriceInfo><PriceInfo><ItemNo>36</ItemNo><ItemCode>SEL0048</ItemCode><SupplierCompCode></SupplierCompCode><RoomTypeCode>9364|NDNRZE|AQCRDG|Q|E|Superior Double|a2dcb9be-b3b8-22e6-b8e1-3770c1ca1b17|NONE|HFJDRMMFG|~None</RoomTypeCode><RoomTypeName><![CDATA[Superior Double]]></RoomTypeName><BreakfastTypeName><![CDATA[None]]></BreakfastTypeName><AddBreakfastTypeName></AddBreakfastTypeName><PriceComment><![CDATA[]]></PriceComment><FareRateType>None</FareRateType><PriceStatus>Available</PriceStatus><NetCurrencyCode>USD</NetCurrencyCode><NetConvertRate>1.00000000</NetConvertRate><SellerNetPrice>1035</SellerNetPrice><LocalNetPrice>1034.66</LocalNetPrice><SellerMarkupPrice>0</SellerMarkupPrice><RecommendClientPrice>1158</RecommendClientPrice><SellerClientPrice>1035</SellerClientPrice><Comment><![CDATA[]]></Comment><DoubleBedYn>false</DoubleBedYn></PriceInfo><PriceInfo><ItemNo>36</ItemNo><ItemCode>SEL0048</ItemCode><SupplierCompCode></SupplierCompCode><RoomTypeCode>9364|AAQTRZB|AZZRNZ|Q|E|Luxury Twin|289e67ab-339d-fcd5-763f-c4b48ee3b9b9|NONE|HZFKRBDKZ|~None</RoomTypeCode><RoomTypeName><![CDATA[Luxury Twin]]></RoomTypeName><BreakfastTypeName><![CDATA[None]]></BreakfastTypeName><AddBreakfastTypeName></AddBreakfastTypeName><PriceComment><![CDATA[]]></PriceComment><FareRateType>None</FareRateType><PriceStatus>Available</PriceStatus><NetCurrencyCode>USD</NetCurrencyCode><NetConvertRate>1.00000000</NetConvertRate><SellerNetPrice>1206</SellerNetPrice><LocalNetPrice>1205.85</LocalNetPrice><SellerMarkupPrice>0</SellerMarkupPrice><RecommendClientPrice>1350</RecommendClientPrice><SellerClientPrice>1206</SellerClientPrice><Comment><![CDATA[]]></Comment><DoubleBedYn>false</DoubleBedYn></PriceInfo><PriceInfo><ItemNo>36</ItemNo><ItemCode>SEL0048</ItemCode><SupplierCompCode></SupplierCompCode><RoomTypeCode>9364|AAQTRZB|AZZRNZ|Q|E|Luxury Double|9c8df68e-71aa-1a35-0beb-538bbdb8460f|NONE|HZFKRBDKZ|~None</RoomTypeCode><RoomTypeName><![CDATA[Luxury Double]]></RoomTypeName><BreakfastTypeName><![CDATA[None]]></BreakfastTypeName><AddBreakfastTypeName></AddBreakfastTypeName><PriceComment><![CDATA[]]></PriceComment><FareRateType>None</FareRateType><PriceStatus>Available</PriceStatus><NetCurrencyCode>USD</NetCurrencyCode><NetConvertRate>1.00000000</NetConvertRate><SellerNetPrice>1206</SellerNetPrice><LocalNetPrice>1205.85</LocalNetPrice><SellerMarkupPrice>0</SellerMarkupPrice><RecommendClientPrice>1350</RecommendClientPrice><SellerClientPrice>1206</SellerClientPrice><Comment><![CDATA[]]></Comment><DoubleBedYn>false</DoubleBedYn></PriceInfo><PriceInfo><ItemNo>36</ItemNo><ItemCode>SEL0048</ItemCode><SupplierCompCode></SupplierCompCode><RoomTypeCode>9364|AACDRAT|AZBRZD|Q|E|Deluxe Twin|32ec4f9c-d7b5-d1b7-2b31-35d45177ed6a|NONE|HZKBRFJDD|~Breakfast</RoomTypeCode><RoomTypeName><![CDATA[Deluxe Twin]]></RoomTypeName><BreakfastTypeName><![CDATA[Breakfast]]></BreakfastTypeName><AddBreakfastTypeName></AddBreakfastTypeName><PriceComment><![CDATA[]]></PriceComment><FareRateType>None</FareRateType><PriceStatus>Available</PriceStatus><NetCurrencyCode>USD</NetCurrencyCode><NetConvertRate>1.00000000</NetConvertRate><SellerNetPrice>1258</SellerNetPrice><LocalNetPrice>1258.03</LocalNetPrice><SellerMarkupPrice>0</SellerMarkupPrice><RecommendClientPrice>1408</RecommendClientPrice><SellerClientPrice>1258</SellerClientPrice><Comment><![CDATA[]]></Comment><DoubleBedYn>false</DoubleBedYn></PriceInfo><PriceInfo><ItemNo>36</ItemNo><ItemCode>SEL0048</ItemCode><SupplierCompCode></SupplierCompCode><RoomTypeCode>9364|AACDRAT|AZBRZD|Q|E|Superior Double|171b4ad3-8835-18d5-59fe-7a9279f9fa32|NONE|HZKBRFJDD|~Breakfast</RoomTypeCode><RoomTypeName><![CDATA[Superior Double]]></RoomTypeName><BreakfastTypeName><![CDATA[Breakfast]]></BreakfastTypeName><AddBreakfastTypeName></AddBreakfastTypeName><PriceComment><![CDATA[]]></PriceComment><FareRateType>None</FareRateType><PriceStatus>Available</PriceStatus><NetCurrencyCode>USD</NetCurrencyCode><NetConvertRate>1.00000000</NetConvertRate><SellerNetPrice>1258</SellerNetPrice><LocalNetPrice>1258.03</LocalNetPrice><SellerMarkupPrice>0</SellerMarkupPrice><RecommendClientPrice>1408</RecommendClientPrice><SellerClientPrice>1258</SellerClientPrice><Comment><![CDATA[]]></Comment><DoubleBedYn>false</DoubleBedYn></PriceInfo><PriceInfo><ItemNo>36</ItemNo><ItemCode>SEL0048</ItemCode><SupplierCompCode></SupplierCompCode><RoomTypeCode>9364|AZGNRBN|ADZRZA|Q|E|Luxury Twin|664321c3-7259-bd81-fef8-dd5a3c360c3f|NONE|HJPKRFBFH|~Breakfast</RoomTypeCode><RoomTypeName><![CDATA[Luxury Twin]]></RoomTypeName><BreakfastTypeName><![CDATA[Breakfast]]></BreakfastTypeName><AddBreakfastTypeName></AddBreakfastTypeName><PriceComment><![CDATA[]]></PriceComment><FareRateType>None</FareRateType><PriceStatus>Available</PriceStatus><NetCurrencyCode>USD</NetCurrencyCode><NetConvertRate>1.00000000</NetConvertRate><SellerNetPrice>1395</SellerNetPrice><LocalNetPrice>1395.08</LocalNetPrice><SellerMarkupPrice>0</SellerMarkupPrice><RecommendClientPrice>1561</RecommendClientPrice><SellerClientPrice>1395</SellerClientPrice><Comment><![CDATA[]]></Comment><DoubleBedYn>false</DoubleBedYn></PriceInfo><PriceInfo><ItemNo>36</ItemNo><ItemCode>SEL0048</ItemCode><SupplierCompCode></SupplierCompCode><RoomTypeCode>9364|AZGNRBN|ADZRZA|Q|E|Luxury Double|9bd29a53-1dd1-0d9d-7f10-e75f1983e4ea|NONE|HJPKRFBFH|~Breakfast</RoomTypeCode><RoomTypeName><![CDATA[Luxury Double]]></RoomTypeName><BreakfastTypeName><![CDATA[Breakfast]]></BreakfastTypeName><AddBreakfastTypeName></AddBreakfastTypeName><PriceComment><![CDATA[]]></PriceComment><FareRateType>None</FareRateType><PriceStatus>Available</PriceStatus><NetCurrencyCode>USD</NetCurrencyCode><NetConvertRate>1.00000000</NetConvertRate><SellerNetPrice>1395</SellerNetPrice><LocalNetPrice>1395.08</LocalNetPrice><SellerMarkupPrice>0</SellerMarkupPrice><RecommendClientPrice>1561</RecommendClientPrice><SellerClientPrice>1395</SellerClientPrice><Comment><![CDATA[]]></Comment><DoubleBedYn>false</DoubleBedYn></PriceInfo><PriceInfo><ItemNo>36</ItemNo><ItemCode>SEL0048</ItemCode><SupplierCompCode></SupplierCompCode><RoomTypeCode>9364|ENTTREN|DDQRGA|Q|E|Suite|0c284b48-55c0-cc7f-1259-d9b7144586f9|NONE|DJZJRJMKH|~None</RoomTypeCode><RoomTypeName><![CDATA[Suite]]></RoomTypeName><BreakfastTypeName><![CDATA[None]]></BreakfastTypeName><AddBreakfastTypeName></AddBreakfastTypeName><PriceComment><![CDATA[]]></PriceComment><FareRateType>None</FareRateType><PriceStatus>Available</PriceStatus><NetCurrencyCode>USD</NetCurrencyCode><NetConvertRate>1.00000000</NetConvertRate><SellerNetPrice>4323</SellerNetPrice><LocalNetPrice>4323.37</LocalNetPrice><SellerMarkupPrice>0</SellerMarkupPrice><RecommendClientPrice>4839</RecommendClientPrice><SellerClientPrice>4323</SellerClientPrice><Comment><![CDATA[]]></Comment><DoubleBedYn>false</DoubleBedYn></PriceInfo></PriceList></HotelItemInfo><HotelItemInfo><ItemCode>SEL0070</ItemCode><ItemName><![CDATA[elle inn hotel]]></ItemName><StarRating></StarRating><RecommendYn>True</RecommendYn><ExpertReportYn>False</ExpertReportYn><FirstImageFileName></FirstImageFileName><HotelDescription><![CDATA[]]></HotelDescription><BackpackYn>True</BackpackYn><BusinessYn>True</BusinessYn><HoneymoonYn>True</HoneymoonYn><FairYn>False</FairYn><AirPackYn>False</AirPackYn><BookingCount>1</BookingCount><LocationList></LocationList><PriceList><PriceInfo><ItemNo>21</ItemNo><ItemCode>SEL0070</ItemCode><SupplierCompCode></SupplierCompCode><RoomTypeCode>77232|BCCRBA|NCRQN|Q|E|Deluxe Twin|3873ec27-9b65-b8eb-0f95-b4203c58405a|NONE|PJZRBJZP|~None</RoomTypeCode><RoomTypeName><![CDATA[Deluxe Twin]]></RoomTypeName><BreakfastTypeName><![CDATA[None]]></BreakfastTypeName><AddBreakfastTypeName></AddBreakfastTypeName><PriceComment><![CDATA[]]></PriceComment><FareRateType>None</FareRateType><PriceStatus>Available</PriceStatus><NetCurrencyCode>USD</NetCurrencyCode><NetConvertRate>1.00000000</NetConvertRate><SellerNetPrice>933</SellerNetPrice><LocalNetPrice>932.83</LocalNetPrice><SellerMarkupPrice>0</SellerMarkupPrice><RecommendClientPrice>1044</RecommendClientPrice><SellerClientPrice>933</SellerClientPrice><Comment><![CDATA[]]></Comment><DoubleBedYn>false</DoubleBedYn></PriceInfo></PriceList></HotelItemInfo><HotelItemInfo><ItemCode>SEL0106</ItemCode><ItemName><![CDATA[millennium seoul hilton hotel]]></ItemName><StarRating>5</StarRating><RecommendYn>False</RecommendYn><ExpertReportYn>False</ExpertReportYn><FirstImageFileName></FirstImageFileName><HotelDescription><![CDATA[]]></HotelDescription><BackpackYn>False</BackpackYn><BusinessYn>False</BusinessYn><HoneymoonYn>False</HoneymoonYn><FairYn>False</FairYn><AirPackYn>False</AirPackYn><BookingCount>1</BookingCount><GeoCode><Latitude>37.5238</Latitude><Longitude>126.9774</Longitude></GeoCode><LocationList></LocationList><PriceList><PriceInfo><ItemNo>28</ItemNo><ItemCode>SEL0106</ItemCode><SupplierCompCode></SupplierCompCode><RoomTypeCode>20200411|20200414|W|435|111653|DBL.DX-KG|ID_B2B_26|RO|ODA3G5|3~1~0||N@04~~2216ac~-563632084~N~~B7C05C0C859941D157892533275902PAAR00000190010000608239607:BFED.FH:double deluxe king bed nrf::A0#B0#C0#D0#E0|HMKHRMHPP|~None</RoomTypeCode><RoomTypeName><![CDATA[double deluxe king bed nrf]]></RoomTypeName><BreakfastTypeName><![CDATA[None]]></BreakfastTypeName><AddBreakfastTypeName></AddBreakfastTypeName><PriceComment><![CDATA[]]></PriceComment><FareRateType>None</FareRateType><PriceStatus>Available</PriceStatus><NetCurrencyCode>USD</NetCurrencyCode><NetConvertRate>1.00000000</NetConvertRate><SellerNetPrice>1652</SellerNetPrice><LocalNetPrice>1651.62</LocalNetPrice><SellerMarkupPrice>0</SellerMarkupPrice><RecommendClientPrice>1883</RecommendClientPrice><SellerClientPrice>1652</SellerClientPrice><Comment><![CDATA[]]></Comment><DoubleBedYn>false</DoubleBedYn><SupplierPromotion><PromotionName><![CDATA[Non-Refundable ]]></PromotionName><PromotionDescription><![CDATA[Non-Refundable ]]></PromotionDescription></SupplierPromotion></PriceInfo><PriceInfo><ItemNo>28</ItemNo><ItemCode>SEL0106</ItemCode><SupplierCompCode></SupplierCompCode><RoomTypeCode>20200411|20200414|W|435|111653|TWN.DX|ID_B2B_26|RO|ODA3G5|3~1~0||N@04~~2216ac~1344461200~N~~B7C05C0C859941D157892533275902PAAR00000190010000608239607:BFED.FH:twin deluxe nrf::A0#B0#C0#D0#E0|HMKHRMHPP|~None</RoomTypeCode><RoomTypeName><![CDATA[twin deluxe nrf]]></RoomTypeName><BreakfastTypeName><![CDATA[None]]></BreakfastTypeName><AddBreakfastTypeName></AddBreakfastTypeName><PriceComment><![CDATA[]]></PriceComment><FareRateType>None</FareRateType><PriceStatus>Available</PriceStatus><NetCurrencyCode>USD</NetCurrencyCode><NetConvertRate>1.00000000</NetConvertRate><SellerNetPrice>1652</SellerNetPrice><LocalNetPrice>1651.62</LocalNetPrice><SellerMarkupPrice>0</SellerMarkupPrice><RecommendClientPrice>1883</RecommendClientPrice><SellerClientPrice>1652</SellerClientPrice><Comment><![CDATA[]]></Comment><DoubleBedYn>false</DoubleBedYn><SupplierPromotion><PromotionName><![CDATA[Non-Refundable ]]></PromotionName><PromotionDescription><![CDATA[Non-Refundable ]]></PromotionDescription></SupplierPromotion></PriceInfo><PriceInfo><ItemNo>28</ItemNo><ItemCode>SEL0106</ItemCode><SupplierCompCode></SupplierCompCode><RoomTypeCode>20200411|20200414|W|435|111653|DBL.VN|ID_B2B_26|RO|ODA3G5|3~1~0||N@04~~24573a~926844699~N~~B7C05C0C859941D157892533275902PAAR00000190010000608211688:BGHC.BH:double mountain view nrf::A0#B0#C0#D0#E0|HGBPRZZHP|~None</RoomTypeCode><RoomTypeName><![CDATA[double mountain view nrf]]></RoomTypeName><BreakfastTypeName><![CDATA[None]]></BreakfastTypeName><AddBreakfastTypeName></AddBreakfastTypeName><PriceComment><![CDATA[]]></PriceComment><FareRateType>None</FareRateType><PriceStatus>Available</PriceStatus><NetCurrencyCode>USD</NetCurrencyCode><NetConvertRate>1.00000000</NetConvertRate><SellerNetPrice>1789</SellerNetPrice><LocalNetPrice>1789.22</LocalNetPrice><SellerMarkupPrice>0</SellerMarkupPrice><RecommendClientPrice>2040</RecommendClientPrice><SellerClientPrice>1789</SellerClientPrice><Comment><![CDATA[]]></Comment><DoubleBedYn>false</DoubleBedYn><SupplierPromotion><PromotionName><![CDATA[Non-Refundable ]]></PromotionName><PromotionDescription><![CDATA[Non-Refundable ]]></PromotionDescription></SupplierPromotion></PriceInfo><PriceInfo><ItemNo>28</ItemNo><ItemCode>SEL0106</ItemCode><SupplierCompCode></SupplierCompCode><RoomTypeCode>20200411|20200414|W|435|111653|TWN.VN|ID_B2B_26|RO|ODAP18|3~1~0||N@04~~2257ae~289469619~N~~B7C05C0C859941D157892533275902PAAR000001900100006082286c4:BHDC.EA:twin mountain view nrf::A0#B0#C0#D0#E0|HBKJRMMB|~None</RoomTypeCode><RoomTypeName><![CDATA[twin mountain view nrf]]></RoomTypeName><BreakfastTypeName><![CDATA[None]]></BreakfastTypeName><AddBreakfastTypeName></AddBreakfastTypeName><PriceComment><![CDATA[]]></PriceComment><FareRateType>None</FareRateType><PriceStatus>Available</PriceStatus><NetCurrencyCode>USD</NetCurrencyCode><NetConvertRate>1.00000000</NetConvertRate><SellerNetPrice>1854</SellerNetPrice><LocalNetPrice>1853.67</LocalNetPrice><SellerMarkupPrice>0</SellerMarkupPrice><RecommendClientPrice>2114</RecommendClientPrice><SellerClientPrice>1854</SellerClientPrice><Comment><![CDATA[]]></Comment><DoubleBedYn>false</DoubleBedYn><SupplierPromotion><PromotionName><![CDATA[Non-Refundable ]]></PromotionName><PromotionDescription><![CDATA[Non-Refundable ]]></PromotionDescription></SupplierPromotion></PriceInfo><PriceInfo><ItemNo>28</ItemNo><ItemCode>SEL0106</ItemCode><SupplierCompCode></SupplierCompCode><RoomTypeCode>20200411|20200414|W|435|111653|DBL.DX-KG|ID_B2B_26|BB|ODA4G5|3~1~0||N@04~~257781~-352553771~N~~B7C05C0C859941D157892533275902PAAR000001900100006082316c8:BHDG.EJ:double deluxe king bed nrf::A0#B0#C0#D0#E0|HBKBRFDDJ|~Breakfast</RoomTypeCode><RoomTypeName><![CDATA[double deluxe king bed nrf]]></RoomTypeName><BreakfastTypeName><![CDATA[Breakfast]]></BreakfastTypeName><AddBreakfastTypeName></AddBreakfastTypeName><PriceComment><![CDATA[]]></PriceComment><FareRateType>None</FareRateType><PriceStatus>Available</PriceStatus><NetCurrencyCode>USD</NetCurrencyCode><NetConvertRate>1.00000000</NetConvertRate><SellerNetPrice>1858</SellerNetPrice><LocalNetPrice>1858.04</LocalNetPrice><SellerMarkupPrice>0</SellerMarkupPrice><RecommendClientPrice>2119</RecommendClientPrice><SellerClientPrice>1858</SellerClientPrice><Comment><![CDATA[]]></Comment><DoubleBedYn>false</DoubleBedYn><SupplierPromotion><PromotionName><![CDATA[Non-Refundable ]]></PromotionName><PromotionDescription><![CDATA[Non-Refundable ]]></PromotionDescription></SupplierPromotion></PriceInfo><PriceInfo><ItemNo>28</ItemNo><ItemCode>SEL0106</ItemCode><SupplierCompCode></SupplierCompCode><RoomTypeCode>20200411|20200414|W|435|111653|TWN.DX|ID_B2B_26|BB|ODA4G5|3~1~0||N@04~~257781~1555539513~N~~B7C05C0C859941D157892533275902PAAR000001900100006082316c8:BHDG.EJ:twin deluxe nrf::A0#B0#C0#D0#E0|HBKBRFDDJ|~Breakfast</RoomTypeCode><RoomTypeName><![CDATA[twin deluxe nrf]]></RoomTypeName><BreakfastTypeName><![CDATA[Breakfast]]></BreakfastTypeName><AddBreakfastTypeName></AddBreakfastTypeName><PriceComment><![CDATA[]]></PriceComment><FareRateType>None</FareRateType><PriceStatus>Available</PriceStatus><NetCurrencyCode>USD</NetCurrencyCode><NetConvertRate>1.00000000</NetConvertRate><SellerNetPrice>1858</SellerNetPrice><LocalNetPrice>1858.04</LocalNetPrice><SellerMarkupPrice>0</SellerMarkupPrice><RecommendClientPrice>2119</RecommendClientPrice><SellerClientPrice>1858</SellerClientPrice><Comment><![CDATA[]]></Comment><DoubleBedYn>false</DoubleBedYn><SupplierPromotion><PromotionName><![CDATA[Non-Refundable ]]></PromotionName><PromotionDescription><![CDATA[Non-Refundable ]]></PromotionDescription></SupplierPromotion></PriceInfo><PriceInfo><ItemNo>28</ItemNo><ItemCode>SEL0106</ItemCode><SupplierCompCode></SupplierCompCode><RoomTypeCode>20200411|20200414|W|435|111653|DBL.DX-KG|ID_B2B_26|RO|ODCC25|3~1~0||N@04~~22a857~-277932671~N~~B7C05C0C859941D157892533275902PAAR00000190010000608210710:BIAI.BG:double deluxe king bed::A0#B0#C0#D0#E0|HPJDRGJHZ|~None</RoomTypeCode><RoomTypeName><![CDATA[double deluxe king bed]]></RoomTypeName><BreakfastTypeName><![CDATA[None]]></BreakfastTypeName><AddBreakfastTypeName></AddBreakfastTypeName><PriceComment><![CDATA[]]></PriceComment><FareRateType>None</FareRateType><PriceStatus>Available</PriceStatus><NetCurrencyCode>USD</NetCurrencyCode><NetConvertRate>1.00000000</NetConvertRate><SellerNetPrice>1935</SellerNetPrice><LocalNetPrice>1934.73</LocalNetPrice><SellerMarkupPrice>0</SellerMarkupPrice><RecommendClientPrice>2206</RecommendClientPrice><SellerClientPrice>1935</SellerClientPrice><Comment><![CDATA[]]></Comment><DoubleBedYn>false</DoubleBedYn></PriceInfo><PriceInfo><ItemNo>28</ItemNo><ItemCode>SEL0106</ItemCode><SupplierCompCode></SupplierCompCode><RoomTypeCode>20200411|20200414|W|435|111653|TWN.DX|ID_B2B_26|RO|ODCC25|3~1~0||N@04~~22a857~1630160613~N~~B7C05C0C859941D157892533275902PAAR00000190010000608210710:BIAI.BG:twin deluxe::A0#B0#C0#D0#E0|HPJDRGJHZ|~None</RoomTypeCode><RoomTypeName><![CDATA[twin deluxe]]></RoomTypeName><BreakfastTypeName><![CDATA[None]]></BreakfastTypeName><AddBreakfastTypeName></AddBreakfastTypeName><PriceComment><![CDATA[]]></PriceComment><FareRateType>None</FareRateType><PriceStatus>Available</PriceStatus><NetCurrencyCode>USD</NetCurrencyCode><NetConvertRate>1.00000000</NetConvertRate><SellerNetPrice>1935</SellerNetPrice><LocalNetPrice>1934.73</LocalNetPrice><SellerMarkupPrice>0</SellerMarkupPrice><RecommendClientPrice>2206</RecommendClientPrice><SellerClientPrice>1935</SellerClientPrice><Comment><![CDATA[]]></Comment><DoubleBedYn>false</DoubleBedYn></PriceInfo><PriceInfo><ItemNo>28</ItemNo><ItemCode>SEL0106</ItemCode><SupplierCompCode></SupplierCompCode><RoomTypeCode>20200411|20200414|W|435|111653|DBL.VN|ID_B2B_26|BB|ODA4G5|3~1~0||N@04~~217810~-1460598730~N~~B7C05C0C859941D157892533275902PAAR0000019001000060820f749:BIGF.BF:double mountain view nrf::A0#B0#C0#D0#E0|HPPKRGHFK|~Breakfast</RoomTypeCode><RoomTypeName><![CDATA[double mountain view nrf]]></RoomTypeName><BreakfastTypeName><![CDATA[Breakfast]]></BreakfastTypeName><AddBreakfastTypeName></AddBreakfastTypeName><PriceComment><![CDATA[]]></PriceComment><FareRateType>None</FareRateType><PriceStatus>Available</PriceStatus><NetCurrencyCode>USD</NetCurrencyCode><NetConvertRate>1.00000000</NetConvertRate><SellerNetPrice>1996</SellerNetPrice><LocalNetPrice>1995.71</LocalNetPrice><SellerMarkupPrice>0</SellerMarkupPrice><RecommendClientPrice>2275</RecommendClientPrice><SellerClientPrice>1996</SellerClientPrice><Comment><![CDATA[]]></Comment><DoubleBedYn>false</DoubleBedYn><SupplierPromotion><PromotionName><![CDATA[Non-Refundable ]]></PromotionName><PromotionDescription><![CDATA[Non-Refundable ]]></PromotionDescription></SupplierPromotion></PriceInfo><PriceInfo><ItemNo>28</ItemNo><ItemCode>SEL0106</ItemCode><SupplierCompCode></SupplierCompCode><RoomTypeCode>20200411|20200414|W|435|111653|TWN.VN|ID_B2B_26|BB|ODA4G5|3~1~0||N@04~~217810~443450937~N~~B7C05C0C859941D157892533275902PAAR0000019001000060820f749:BIGF.BF:twin mountain view nrf::A0#B0#C0#D0#E0|HPPKRGHFK|~Breakfast</RoomTypeCode><RoomTypeName><![CDATA[twin mountain view nrf]]></RoomTypeName><BreakfastTypeName><![CDATA[Breakfast]]></BreakfastTypeName><AddBreakfastTypeName></AddBreakfastTypeName><PriceComment><![CDATA[]]></PriceComment><FareRateType>None</FareRateType><PriceStatus>Available</PriceStatus><NetCurrencyCode>USD</NetCurrencyCode><NetConvertRate>1.00000000</NetConvertRate><SellerNetPrice>1996</SellerNetPrice><LocalNetPrice>1995.71</LocalNetPrice><SellerMarkupPrice>0</SellerMarkupPrice><RecommendClientPrice>2275</RecommendClientPrice><SellerClientPrice>1996</SellerClientPrice><Comment><![CDATA[]]></Comment><DoubleBedYn>false</DoubleBedYn><SupplierPromotion><PromotionName><![CDATA[Non-Refundable ]]></PromotionName><PromotionDescription><![CDATA[Non-Refundable ]]></PromotionDescription></SupplierPromotion></PriceInfo><PriceInfo><ItemNo>28</ItemNo><ItemCode>SEL0106</ItemCode><SupplierCompCode></SupplierCompCode><RoomTypeCode>20200411|20200414|W|435|111653|DBL.VN|ID_B2B_26|RO|ODCC25|3~1~0||N@04~~225909~-1275354737~N~~B7C05C0C859941D157892533275902PAAR000001900100006082557a6:BJFI.IF:double mountain view::A0#B0#C0#D0#E0|ZFPKRPMPK|~None</RoomTypeCode><RoomTypeName><![CDATA[double mountain view]]></RoomTypeName><BreakfastTypeName><![CDATA[None]]></BreakfastTypeName><AddBreakfastTypeName></AddBreakfastTypeName><PriceComment><![CDATA[]]></PriceComment><FareRateType>None</FareRateType><PriceStatus>Available</PriceStatus><NetCurrencyCode>USD</NetCurrencyCode><NetConvertRate>1.00000000</NetConvertRate><SellerNetPrice>2096</SellerNetPrice><LocalNetPrice>2095.97</LocalNetPrice><SellerMarkupPrice>0</SellerMarkupPrice><RecommendClientPrice>2390</RecommendClientPrice><SellerClientPrice>2096</SellerClientPrice><Comment><![CDATA[]]></Comment><DoubleBedYn>false</DoubleBedYn></PriceInfo><PriceInfo><ItemNo>28</ItemNo><ItemCode>SEL0106</ItemCode><SupplierCompCode></SupplierCompCode><RoomTypeCode>20200411|20200414|W|435|111653|TWN.VN|ID_B2B_26|RO|ODCC25|3~1~0||N@04~~225909~628694930~N~~B7C05C0C859941D157892533275902PAAR000001900100006082557a6:BJFI.IF:twin mountain view::A0#B0#C0#D0#E0|ZFPKRPMPK|~None</RoomTypeCode><RoomTypeName><![CDATA[twin mountain view]]></RoomTypeName><BreakfastTypeName><![CDATA[None]]></BreakfastTypeName><AddBreakfastTypeName></AddBreakfastTypeName><PriceComment><![CDATA[]]></PriceComment><FareRateType>None</FareRateType><PriceStatus>Available</PriceStatus><NetCurrencyCode>USD</NetCurrencyCode><NetConvertRate>1.00000000</NetConvertRate><SellerNetPrice>2096</SellerNetPrice><LocalNetPrice>2095.97</LocalNetPrice><SellerMarkupPrice>0</SellerMarkupPrice><RecommendClientPrice>2390</RecommendClientPrice><SellerClientPrice>2096</SellerClientPrice><Comment><![CDATA[]]></Comment><DoubleBedYn>false</DoubleBedYn></PriceInfo><PriceInfo><ItemNo>28</ItemNo><ItemCode>SEL0106</ItemCode><SupplierCompCode></SupplierCompCode><RoomTypeCode>20200411|20200414|W|435|111653|DBL.EJ-KG|ID_B2B_26|RO|ODAP18|3~1~0||N@04~~24d8e5~1866469106~N~~B7C05C0C859941D157892533275902PAAR0000019001000060824d7d6:CAAG.HH:double executive king bed nrf::A0#B0#C0#D0#E0|ZHDGRZDJP|~None</RoomTypeCode><RoomTypeName><![CDATA[double executive king bed nrf]]></RoomTypeName><BreakfastTypeName><![CDATA[None]]></BreakfastTypeName><AddBreakfastTypeName></AddBreakfastTypeName><PriceComment><![CDATA[]]></PriceComment><FareRateType>None</FareRateType><PriceStatus>Available</PriceStatus><NetCurrencyCode>USD</NetCurrencyCode><NetConvertRate>1.00000000</NetConvertRate><SellerNetPrice>2147</SellerNetPrice><LocalNetPrice>2147.24</LocalNetPrice><SellerMarkupPrice>0</SellerMarkupPrice><RecommendClientPrice>2448</RecommendClientPrice><SellerClientPrice>2147</SellerClientPrice><Comment><![CDATA[]]></Comment><DoubleBedYn>false</DoubleBedYn><SupplierPromotion><PromotionName><![CDATA[Non-Refundable ]]></PromotionName><PromotionDescription><![CDATA[Non-Refundable ]]></PromotionDescription></SupplierPromotion></PriceInfo><PriceInfo><ItemNo>28</ItemNo><ItemCode>SEL0106</ItemCode><SupplierCompCode></SupplierCompCode><RoomTypeCode>20200411|20200414|W|435|111653|DBL.DX-KG|ID_B2B_26|BB|ODBB25|3~1~0||N@04~~222962~1134125647~N~~B7C05C0C859941D157892533275902PAAR000001900100006082167f2:CADE.CC:double deluxe king bed::A0#B0#C0#D0#E0|ZHGMRMHKD|~Breakfast</RoomTypeCode><RoomTypeName><![CDATA[double deluxe king bed]]></RoomTypeName><BreakfastTypeName><![CDATA[Breakfast]]></BreakfastTypeName><AddBreakfastTypeName></AddBreakfastTypeName><PriceComment><![CDATA[]]></PriceComment><FareRateType>None</FareRateType><PriceStatus>Available</PriceStatus><NetCurrencyCode>USD</NetCurrencyCode><NetConvertRate>1.00000000</NetConvertRate><SellerNetPrice>2177</SellerNetPrice><LocalNetPrice>2176.62</LocalNetPrice><SellerMarkupPrice>0</SellerMarkupPrice><RecommendClientPrice>2482</RecommendClientPrice><SellerClientPrice>2177</SellerClientPrice><Comment><![CDATA[]]></Comment><DoubleBedYn>false</DoubleBedYn></PriceInfo><PriceInfo><ItemNo>28</ItemNo><ItemCode>SEL0106</ItemCode><SupplierCompCode></SupplierCompCode><RoomTypeCode>20200411|20200414|W|435|111653|TWN.DX|ID_B2B_26|BB|ODBB25|3~1~0||N@04~~222962~-1252748365~N~~B7C05C0C859941D157892533275902PAAR000001900100006082167f2:CADE.CC:twin deluxe::A0#B0#C0#D0#E0|ZHGMRMHKD|~Breakfast</RoomTypeCode><RoomTypeName><![CDATA[twin deluxe]]></RoomTypeName><BreakfastTypeName><![CDATA[Breakfast]]></BreakfastTypeName><AddBreakfastTypeName></AddBreakfastTypeName><PriceComment><![CDATA[]]></PriceComment><FareRateType>None</FareRateType><PriceStatus>Available</PriceStatus><NetCurrencyCode>USD</NetCurrencyCode><NetConvertRate>1.00000000</NetConvertRate><SellerNetPrice>2177</SellerNetPrice><LocalNetPrice>2176.62</LocalNetPrice><SellerMarkupPrice>0</SellerMarkupPrice><RecommendClientPrice>2482</RecommendClientPrice><SellerClientPrice>2177</SellerClientPrice><Comment><![CDATA[]]></Comment><DoubleBedYn>false</DoubleBedYn></PriceInfo><PriceInfo><ItemNo>28</ItemNo><ItemCode>SEL0106</ItemCode><SupplierCompCode></SupplierCompCode><RoomTypeCode>20200411|20200414|W|435|111653|ROO.EJ|ID_B2B_26|RO|ODAP18|3~1~0||N@04~~20e974~-1746080300~N~~B7C05C0C859941D157892533275902PAAR00000190010000608215854:CBDC.CB:room executive nrf::A0#B0#C0#D0#E0|ZZBHRDMDG|~None</RoomTypeCode><RoomTypeName><![CDATA[room executive nrf]]></RoomTypeName><BreakfastTypeName><![CDATA[None]]></BreakfastTypeName><AddBreakfastTypeName></AddBreakfastTypeName><PriceComment><![CDATA[]]></PriceComment><FareRateType>None</FareRateType><PriceStatus>Available</PriceStatus><NetCurrencyCode>USD</NetCurrencyCode><NetConvertRate>1.00000000</NetConvertRate><SellerNetPrice>2281</SellerNetPrice><LocalNetPrice>2281.46</LocalNetPrice><SellerMarkupPrice>0</SellerMarkupPrice><RecommendClientPrice>2601</RecommendClientPrice><SellerClientPrice>2281</SellerClientPrice><Comment><![CDATA[]]></Comment><DoubleBedYn>false</DoubleBedYn><SupplierPromotion><PromotionName><![CDATA[Non-Refundable ]]></PromotionName><PromotionDescription><![CDATA[Non-Refundable ]]></PromotionDescription></SupplierPromotion></PriceInfo><PriceInfo><ItemNo>28</ItemNo><ItemCode>SEL0106</ItemCode><SupplierCompCode></SupplierCompCode><RoomTypeCode>20200411|20200414|W|435|111653|JSU.ST|ID_B2B_26|RO|ODAP18|3~1~0||N@04~~2079a5~-2143034149~N~~B7C05C0C859941D157892533275902PAAR0000019001000060821e87f:CBHF.DA:junior suite standard nrf::A0#B0#C0#D0#E0|ZJZGRKGH|~None</RoomTypeCode><RoomTypeName><![CDATA[junior suite standard nrf]]></RoomTypeName><BreakfastTypeName><![CDATA[None]]></BreakfastTypeName><AddBreakfastTypeName></AddBreakfastTypeName><PriceComment><![CDATA[]]></PriceComment><FareRateType>None</FareRateType><PriceStatus>Available</PriceStatus><NetCurrencyCode>USD</NetCurrencyCode><NetConvertRate>1.00000000</NetConvertRate><SellerNetPrice>2328</SellerNetPrice><LocalNetPrice>2327.57</LocalNetPrice><SellerMarkupPrice>0</SellerMarkupPrice><RecommendClientPrice>2654</RecommendClientPrice><SellerClientPrice>2328</SellerClientPrice><Comment><![CDATA[]]></Comment><DoubleBedYn>false</DoubleBedYn><SupplierPromotion><PromotionName><![CDATA[Non-Refundable ]]></PromotionName><PromotionDescription><![CDATA[Non-Refundable ]]></PromotionDescription></SupplierPromotion></PriceInfo><PriceInfo><ItemNo>28</ItemNo><ItemCode>SEL0106</ItemCode><SupplierCompCode></SupplierCompCode><RoomTypeCode>20200411|20200414|W|435|111653|DBL.VN|ID_B2B_26|BB|ODBB25|3~1~0||N@04~~21da14~33706343~N~~B7C05C0C859941D157892533275902PAAR00000190010000608258888:CBIE.II:double mountain view::A0#B0#C0#D0#E0|ZJJGRBZHM|~Breakfast</RoomTypeCode><RoomTypeName><![CDATA[double mountain view]]></RoomTypeName><BreakfastTypeName><![CDATA[Breakfast]]></BreakfastTypeName><AddBreakfastTypeName></AddBreakfastTypeName><PriceComment><![CDATA[]]></PriceComment><FareRateType>None</FareRateType><PriceStatus>Available</PriceStatus><NetCurrencyCode>USD</NetCurrencyCode><NetConvertRate>1.00000000</NetConvertRate><SellerNetPrice>2338</SellerNetPrice><LocalNetPrice>2337.82</LocalNetPrice><SellerMarkupPrice>0</SellerMarkupPrice><RecommendClientPrice>2666</RecommendClientPrice><SellerClientPrice>2338</SellerClientPrice><Comment><![CDATA[]]></Comment><DoubleBedYn>false</DoubleBedYn></PriceInfo><PriceInfo><ItemNo>28</ItemNo><ItemCode>SEL0106</ItemCode><SupplierCompCode></SupplierCompCode><RoomTypeCode>20200411|20200414|W|435|111653|TWN.VN|ID_B2B_26|BB|ODBB25|3~1~0||N@04~~21da14~1937756010~N~~B7C05C0C859941D157892533275902PAAR00000190010000608258888:CBIE.II:twin mountain view::A0#B0#C0#D0#E0|ZJJGRBZHM|~Breakfast</RoomTypeCode><RoomTypeName><![CDATA[twin mountain view]]></RoomTypeName><BreakfastTypeName><![CDATA[Breakfast]]></BreakfastTypeName><AddBreakfastTypeName></AddBreakfastTypeName><PriceComment><![CDATA[]]></PriceComment><FareRateType>None</FareRateType><PriceStatus>Available</PriceStatus><NetCurrencyCode>USD</NetCurrencyCode><NetConvertRate>1.00000000</NetConvertRate><SellerNetPrice>2338</SellerNetPrice><LocalNetPrice>2337.82</LocalNetPrice><SellerMarkupPrice>0</SellerMarkupPrice><RecommendClientPrice>2666</RecommendClientPrice><SellerClientPrice>2338</SellerClientPrice><Comment><![CDATA[]]></Comment><DoubleBedYn>false</DoubleBedYn></PriceInfo><PriceInfo><ItemNo>28</ItemNo><ItemCode>SEL0106</ItemCode><SupplierCompCode></SupplierCompCode><RoomTypeCode>20200411|20200414|W|435|111653|DBL.EJ-KG|ID_B2B_26|BB|ODA4G5|3~1~0||N@04~~2209bb~-1436845062~N~~B7C05C0C859941D157892533275902PAAR000001900100006082018cb:CCFB.AB:double executive king bed nrf::A0#B0#C0#D0#E0|ZDFBRKBFG|~Breakfast</RoomTypeCode><RoomTypeName><![CDATA[double executive king bed nrf]]></RoomTypeName><BreakfastTypeName><![CDATA[Breakfast]]></BreakfastTypeName><AddBreakfastTypeName></AddBreakfastTypeName><PriceComment><![CDATA[]]></PriceComment><FareRateType>None</FareRateType><PriceStatus>Available</PriceStatus><NetCurrencyCode>USD</NetCurrencyCode><NetConvertRate>1.00000000</NetConvertRate><SellerNetPrice>2409</SellerNetPrice><LocalNetPrice>2408.58</LocalNetPrice><SellerMarkupPrice>0</SellerMarkupPrice><RecommendClientPrice>2746</RecommendClientPrice><SellerClientPrice>2409</SellerClientPrice><Comment><![CDATA[]]></Comment><DoubleBedYn>false</DoubleBedYn><SupplierPromotion><PromotionName><![CDATA[Non-Refundable ]]></PromotionName><PromotionDescription><![CDATA[Non-Refundable ]]></PromotionDescription></SupplierPromotion></PriceInfo><PriceInfo><ItemNo>28</ItemNo><ItemCode>SEL0106</ItemCode><SupplierCompCode></SupplierCompCode><RoomTypeCode>20200411|20200414|W|435|111653|ROO.EJ|ID_B2B_26|BB|ODA4G5|3~1~0||N@04~~244a49~39251479~N~~B7C05C0C859941D157892533275902PAAR0000019001000060824294b:CDHJ.GG:room executive nrf::A0#B0#C0#D0#E0|ZKDMRZJMZ|~Breakfast</RoomTypeCode><RoomTypeName><![CDATA[room executive nrf]]></RoomTypeName><BreakfastTypeName><![CDATA[Breakfast]]></BreakfastTypeName><AddBreakfastTypeName></AddBreakfastTypeName><PriceComment><![CDATA[]]></PriceComment><FareRateType>None</FareRateType><PriceStatus>Available</PriceStatus><NetCurrencyCode>USD</NetCurrencyCode><NetConvertRate>1.00000000</NetConvertRate><SellerNetPrice>2546</SellerNetPrice><LocalNetPrice>2546.24</LocalNetPrice><SellerMarkupPrice>0</SellerMarkupPrice><RecommendClientPrice>2903</RecommendClientPrice><SellerClientPrice>2546</SellerClientPrice><Comment><![CDATA[]]></Comment><DoubleBedYn>false</DoubleBedYn><SupplierPromotion><PromotionName><![CDATA[Non-Refundable ]]></PromotionName><PromotionDescription><![CDATA[Non-Refundable ]]></PromotionDescription></SupplierPromotion></PriceInfo><PriceInfo><ItemNo>28</ItemNo><ItemCode>SEL0106</ItemCode><SupplierCompCode></SupplierCompCode><RoomTypeCode>20200411|20200414|W|435|111653|DBL.EJ-KG|ID_B2B_26|RO|ODCC25|3~1~0||N@04~~216b1f~24722901~N~~B7C05C0C859941D157892533275902PAAR0000019001000060825d96a:CEBA.JD:double executive king bed::A0#B0#C0#D0#E0|ZKGPRMPKH|~None</RoomTypeCode><RoomTypeName><![CDATA[double executive king bed]]></RoomTypeName><BreakfastTypeName><![CDATA[None]]></BreakfastTypeName><AddBreakfastTypeName></AddBreakfastTypeName><PriceComment><![CDATA[]]></PriceComment><FareRateType>None</FareRateType><PriceStatus>Available</PriceStatus><NetCurrencyCode>USD</NetCurrencyCode><NetConvertRate>1.00000000</NetConvertRate><SellerNetPrice>2580</SellerNetPrice><LocalNetPrice>2579.70</LocalNetPrice><SellerMarkupPrice>0</SellerMarkupPrice><RecommendClientPrice>2941</RecommendClientPrice><SellerClientPrice>2580</SellerClientPrice><Comment><![CDATA[]]></Comment><DoubleBedYn>false</DoubleBedYn></PriceInfo><PriceInfo><ItemNo>28</ItemNo><ItemCode>SEL0106</ItemCode><SupplierCompCode></SupplierCompCode><RoomTypeCode>20200411|20200414|W|435|111653|ROO.EJ|ID_B2B_26|RO|ODCC25|3~1~0||N@04~~211bd1~939228536~N~~B7C05C0C859941D157892533275902PAAR00000190010000608239a01:CFGB.FH:room executive::A0#B0#C0#D0#E0|ZGDFRBGPP|~None</RoomTypeCode><RoomTypeName><![CDATA[room executive]]></RoomTypeName><BreakfastTypeName><![CDATA[None]]></BreakfastTypeName><AddBreakfastTypeName></AddBreakfastTypeName><PriceComment><![CDATA[]]></PriceComment><FareRateType>None</FareRateType><PriceStatus>Available</PriceStatus><NetCurrencyCode>USD</NetCurrencyCode><NetConvertRate>1.00000000</NetConvertRate><SellerNetPrice>2741</SellerNetPrice><LocalNetPrice>2740.88</LocalNetPrice><SellerMarkupPrice>0</SellerMarkupPrice><RecommendClientPrice>3125</RecommendClientPrice><SellerClientPrice>2741</SellerClientPrice><Comment><![CDATA[]]></Comment><DoubleBedYn>false</DoubleBedYn></PriceInfo><PriceInfo><ItemNo>28</ItemNo><ItemCode>SEL0106</ItemCode><SupplierCompCode></SupplierCompCode><RoomTypeCode>20200411|20200414|W|435|111653|JSU.ST|ID_B2B_26|BB|ODA4G5|3~1~0||N@04~~216b1f~866253409~N~~B7C05C0C859941D157892533275902PAAR0000019001000060823ba0c:CFHC.FJ:junior suite standard nrf::A0#B0#C0#D0#E0|ZGKZRMGHJ|~Breakfast</RoomTypeCode><RoomTypeName><![CDATA[junior suite standard nrf]]></RoomTypeName><BreakfastTypeName><![CDATA[Breakfast]]></BreakfastTypeName><AddBreakfastTypeName></AddBreakfastTypeName><PriceComment><![CDATA[]]></PriceComment><FareRateType>None</FareRateType><PriceStatus>Available</PriceStatus><NetCurrencyCode>USD</NetCurrencyCode><NetConvertRate>1.00000000</NetConvertRate><SellerNetPrice>2753</SellerNetPrice><LocalNetPrice>2752.67</LocalNetPrice><SellerMarkupPrice>0</SellerMarkupPrice><RecommendClientPrice>3139</RecommendClientPrice><SellerClientPrice>2753</SellerClientPrice><Comment><![CDATA[]]></Comment><DoubleBedYn>false</DoubleBedYn><SupplierPromotion><PromotionName><![CDATA[Non-Refundable ]]></PromotionName><PromotionDescription><![CDATA[Non-Refundable ]]></PromotionDescription></SupplierPromotion></PriceInfo><PriceInfo><ItemNo>28</ItemNo><ItemCode>SEL0106</ItemCode><SupplierCompCode></SupplierCompCode><RoomTypeCode>20200411|20200414|W|435|111653|DBL.EJ-KG|ID_B2B_26|BB|ODBB25|3~1~0||N@04~~20fc2a~-511481944~N~~B7C05C0C859941D157892533275902PAAR0000019001000060825da4c:CGDG.JD:double executive king bed::A0#B0#C0#D0#E0|ZBZHRKHKH|~Breakfast</RoomTypeCode><RoomTypeName><![CDATA[double executive king bed]]></RoomTypeName><BreakfastTypeName><![CDATA[Breakfast]]></BreakfastTypeName><AddBreakfastTypeName></AddBreakfastTypeName><PriceComment><![CDATA[]]></PriceComment><FareRateType>None</FareRateType><PriceStatus>Available</PriceStatus><NetCurrencyCode>USD</NetCurrencyCode><NetConvertRate>1.00000000</NetConvertRate><SellerNetPrice>2822</SellerNetPrice><LocalNetPrice>2821.52</LocalNetPrice><SellerMarkupPrice>0</SellerMarkupPrice><RecommendClientPrice>3217</RecommendClientPrice><SellerClientPrice>2822</SellerClientPrice><Comment><![CDATA[]]></Comment><DoubleBedYn>false</DoubleBedYn></PriceInfo><PriceInfo><ItemNo>28</ItemNo><ItemCode>SEL0106</ItemCode><SupplierCompCode></SupplierCompCode><RoomTypeCode>20200411|20200414|W|435|111653|ROO.EJ|ID_B2B_26|BB|ODBB25|3~1~0||N@04~~20acdc~-309583589~N~~B7C05C0C859941D157892533275902PAAR0000019001000060823bae3:CHIH.FJ:room executive::A0#B0#C0#D0#E0|ZPBZRGZHJ|~Breakfast</RoomTypeCode><RoomTypeName><![CDATA[room executive]]></RoomTypeName><BreakfastTypeName><![CDATA[Breakfast]]></BreakfastTypeName><AddBreakfastTypeName></AddBreakfastTypeName><PriceComment><![CDATA[]]></PriceComment><FareRateType>None</FareRateType><PriceStatus>Available</PriceStatus><NetCurrencyCode>USD</NetCurrencyCode><NetConvertRate>1.00000000</NetConvertRate><SellerNetPrice>2983</SellerNetPrice><LocalNetPrice>2982.72</LocalNetPrice><SellerMarkupPrice>0</SellerMarkupPrice><RecommendClientPrice>3401</RecommendClientPrice><SellerClientPrice>2983</SellerClientPrice><Comment><![CDATA[]]></Comment><DoubleBedYn>false</DoubleBedYn></PriceInfo><PriceInfo><ItemNo>28</ItemNo><ItemCode>SEL0106</ItemCode><SupplierCompCode></SupplierCompCode><RoomTypeCode>20200411|20200414|W|435|111653|JSU.ST|ID_B2B_26|RO|ODCC25|3~1~0||N@04~~20acdc~1917776224~N~~B7C05C0C859941D157892533275902PAAR0000019001000060823bae3:CHIH.FJ:junior suite standard::A0#B0#C0#D0#E0|ZPBZRGZHJ|~None</RoomTypeCode><RoomTypeName><![CDATA[junior suite standard]]></RoomTypeName><BreakfastTypeName><![CDATA[None]]></BreakfastTypeName><AddBreakfastTypeName></AddBreakfastTypeName><PriceComment><![CDATA[]]></PriceComment><FareRateType>None</FareRateType><PriceStatus>Available</PriceStatus><NetCurrencyCode>USD</NetCurrencyCode><NetConvertRate>1.00000000</NetConvertRate><SellerNetPrice>2983</SellerNetPrice><LocalNetPrice>2982.72</LocalNetPrice><SellerMarkupPrice>0</SellerMarkupPrice><RecommendClientPrice>3401</RecommendClientPrice><SellerClientPrice>2983</SellerClientPrice><Comment><![CDATA[]]></Comment><DoubleBedYn>false</DoubleBedYn></PriceInfo><PriceInfo><ItemNo>28</ItemNo><ItemCode>SEL0106</ItemCode><SupplierCompCode></SupplierCompCode><RoomTypeCode>20200411|20200414|W|435|111653|JSU.ST|ID_B2B_26|BB|ODBB25|3~1~0||N@04~~203de7~364920887~N~~B7C05C0C859941D157892533275902PAAR00000190010000608240bc5:DABD.GE:junior suite standard::A0#B0#C0#D0#E0|JZZDRKPDB|~Breakfast</RoomTypeCode><RoomTypeName><![CDATA[junior suite standard]]></RoomTypeName><BreakfastTypeName><![CDATA[Breakfast]]></BreakfastTypeName><AddBreakfastTypeName></AddBreakfastTypeName><PriceComment><![CDATA[]]></PriceComment><FareRateType>None</FareRateType><PriceStatus>Available</PriceStatus><NetCurrencyCode>USD</NetCurrencyCode><NetConvertRate>1.00000000</NetConvertRate><SellerNetPrice>3225</SellerNetPrice><LocalNetPrice>3224.59</LocalNetPrice><SellerMarkupPrice>0</SellerMarkupPrice><RecommendClientPrice>3677</RecommendClientPrice><SellerClientPrice>3225</SellerClientPrice><Comment><![CDATA[]]></Comment><DoubleBedYn>false</DoubleBedYn></PriceInfo><PriceInfo><ItemNo>28</ItemNo><ItemCode>SEL0106</ItemCode><SupplierCompCode></SupplierCompCode><RoomTypeCode>20200411|20200414|W|435|111653|SUI.EJ|ID_B2B_26|RO|ODAP18|3~1~0||N@04~~233e13~-1763508123~N~~B7C05C0C859941D157892533275902PAAR0000019001000060824dc66:DBHE.HH:suite executive nrf::A0#B0#C0#D0#E0|JJPGRFFJP|~None</RoomTypeCode><RoomTypeName><![CDATA[suite executive nrf]]></RoomTypeName><BreakfastTypeName><![CDATA[None]]></BreakfastTypeName><AddBreakfastTypeName></AddBreakfastTypeName><PriceComment><![CDATA[]]></PriceComment><FareRateType>None</FareRateType><PriceStatus>Available</PriceStatus><NetCurrencyCode>USD</NetCurrencyCode><NetConvertRate>1.00000000</NetConvertRate><SellerNetPrice>3397</SellerNetPrice><LocalNetPrice>3397.00</LocalNetPrice><SellerMarkupPrice>0</SellerMarkupPrice><RecommendClientPrice>3873</RecommendClientPrice><SellerClientPrice>3397</SellerClientPrice><Comment><![CDATA[]]></Comment><DoubleBedYn>false</DoubleBedYn><SupplierPromotion><PromotionName><![CDATA[Non-Refundable ]]></PromotionName><PromotionDescription><![CDATA[Non-Refundable ]]></PromotionDescription></SupplierPromotion></PriceInfo><PriceInfo><ItemNo>28</ItemNo><ItemCode>SEL0106</ItemCode><SupplierCompCode></SupplierCompCode><RoomTypeCode>20200411|20200414|W|435|111653|SUI.EJ|ID_B2B_26|BB|ODA4G5|3~1~0||N@04~~21dfd9~1152212321~N~~B7C05C0C859941D157892533275902PAAR00000190010000608261e51:DGGF.JH:suite executive nrf::A0#B0#C0#D0#E0|JPZZRKBGP|~Breakfast</RoomTypeCode><RoomTypeName><![CDATA[suite executive nrf]]></RoomTypeName><BreakfastTypeName><![CDATA[Breakfast]]></BreakfastTypeName><AddBreakfastTypeName></AddBreakfastTypeName><PriceComment><![CDATA[]]></PriceComment><FareRateType>None</FareRateType><PriceStatus>Available</PriceStatus><NetCurrencyCode>USD</NetCurrencyCode><NetConvertRate>1.00000000</NetConvertRate><SellerNetPrice>3923</SellerNetPrice><LocalNetPrice>3922.59</LocalNetPrice><SellerMarkupPrice>0</SellerMarkupPrice><RecommendClientPrice>4472</RecommendClientPrice><SellerClientPrice>3923</SellerClientPrice><Comment><![CDATA[]]></Comment><DoubleBedYn>false</DoubleBedYn><SupplierPromotion><PromotionName><![CDATA[Non-Refundable ]]></PromotionName><PromotionDescription><![CDATA[Non-Refundable ]]></PromotionDescription></SupplierPromotion></PriceInfo><PriceInfo><ItemNo>28</ItemNo><ItemCode>SEL0106</ItemCode><SupplierCompCode></SupplierCompCode><RoomTypeCode>20200411|20200414|W|435|111653|SUI.PE|ID_B2B_26|RO|ODAP18|3~1~0||N@04~~25310ae~762883560~N~~B7C05C0C859941D157892533275902PAAR00000190010000608245eb2:DHGC.GJ:suite premier nrf::A0#B0#C0#D0#E0|DFZMRFGBJ|~None</RoomTypeCode><RoomTypeName><![CDATA[suite premier nrf]]></RoomTypeName><BreakfastTypeName><![CDATA[None]]></BreakfastTypeName><AddBreakfastTypeName></AddBreakfastTypeName><PriceComment><![CDATA[]]></PriceComment><FareRateType>None</FareRateType><PriceStatus>Available</PriceStatus><NetCurrencyCode>USD</NetCurrencyCode><NetConvertRate>1.00000000</NetConvertRate><SellerNetPrice>4026</SellerNetPrice><LocalNetPrice>4026.08</LocalNetPrice><SellerMarkupPrice>0</SellerMarkupPrice><RecommendClientPrice>4590</RecommendClientPrice><SellerClientPrice>4026</SellerClientPrice><Comment><![CDATA[]]></Comment><DoubleBedYn>false</DoubleBedYn><SupplierPromotion><PromotionName><![CDATA[Non-Refundable ]]></PromotionName><PromotionDescription><![CDATA[Non-Refundable ]]></PromotionDescription></SupplierPromotion></PriceInfo><PriceInfo><ItemNo>28</ItemNo><ItemCode>SEL0106</ItemCode><SupplierCompCode></SupplierCompCode><RoomTypeCode>20200411|20200414|W|435|111653|SUI.EJ|ID_B2B_26|RO|ODCC25|3~1~0||N@04~~24512c4~507048120~N~~B7C05C0C859941D157892533275902PAAR00000190010000608228fe4:EAGI.EA:suite executive::A0#B0#C0#D0#E0|DJKJRHBB|~None</RoomTypeCode><RoomTypeName><![CDATA[suite executive]]></RoomTypeName><BreakfastTypeName><![CDATA[None]]></BreakfastTypeName><AddBreakfastTypeName></AddBreakfastTypeName><PriceComment><![CDATA[]]></PriceComment><FareRateType>None</FareRateType><PriceStatus>Available</PriceStatus><NetCurrencyCode>USD</NetCurrencyCode><NetConvertRate>1.00000000</NetConvertRate><SellerNetPrice>4353</SellerNetPrice><LocalNetPrice>4353.19</LocalNetPrice><SellerMarkupPrice>0</SellerMarkupPrice><RecommendClientPrice>4963</RecommendClientPrice><SellerClientPrice>4353</SellerClientPrice><Comment><![CDATA[]]></Comment><DoubleBedYn>false</DoubleBedYn></PriceInfo><PriceInfo><ItemNo>28</ItemNo><ItemCode>SEL0106</ItemCode><SupplierCompCode></SupplierCompCode><RoomTypeCode>20200411|20200414|W|435|111653|SUI.EJ|ID_B2B_26|BB|ODBB25|3~1~0||N@04~~23d13cf~1786963248~N~~B7C05C0C859941D157892533275902PAAR0000019001000060822a10c6:ECJE.EC:suite executive::A0#B0#C0#D0#E0|DKPKRFZPD|~Breakfast</RoomTypeCode><RoomTypeName><![CDATA[suite executive]]></RoomTypeName><BreakfastTypeName><![CDATA[Breakfast]]></BreakfastTypeName><AddBreakfastTypeName></AddBreakfastTypeName><PriceComment><![CDATA[]]></PriceComment><FareRateType>None</FareRateType><PriceStatus>Available</PriceStatus><NetCurrencyCode>USD</NetCurrencyCode><NetConvertRate>1.00000000</NetConvertRate><SellerNetPrice>4595</SellerNetPrice><LocalNetPrice>4595.03</LocalNetPrice><SellerMarkupPrice>0</SellerMarkupPrice><RecommendClientPrice>5239</RecommendClientPrice><SellerClientPrice>4595</SellerClientPrice><Comment><![CDATA[]]></Comment><DoubleBedYn>false</DoubleBedYn></PriceInfo><PriceInfo><ItemNo>28</ItemNo><ItemCode>SEL0106</ItemCode><SupplierCompCode></SupplierCompCode><RoomTypeCode>20200411|20200414|W|435|111653|SUI.PE|ID_B2B_26|BB|ODA4G5|3~1~0||N@04~~20a12a1~1985406825~N~~B7C05C0C859941D157892533275902PAAR0000019001000060820810d5:EDAJ.AI:suite premier nrf::A0#B0#C0#D0#E0|DMHFRGHKM|~Breakfast</RoomTypeCode><RoomTypeName><![CDATA[suite premier nrf]]></RoomTypeName><BreakfastTypeName><![CDATA[Breakfast]]></BreakfastTypeName><AddBreakfastTypeName></AddBreakfastTypeName><PriceComment><![CDATA[]]></PriceComment><FareRateType>None</FareRateType><PriceStatus>Available</PriceStatus><NetCurrencyCode>USD</NetCurrencyCode><NetConvertRate>1.00000000</NetConvertRate><SellerNetPrice>4611</SellerNetPrice><LocalNetPrice>4610.72</LocalNetPrice><SellerMarkupPrice>0</SellerMarkupPrice><RecommendClientPrice>5257</RecommendClientPrice><SellerClientPrice>4611</SellerClientPrice><Comment><![CDATA[]]></Comment><DoubleBedYn>false</DoubleBedYn><SupplierPromotion><PromotionName><![CDATA[Non-Refundable ]]></PromotionName><PromotionDescription><![CDATA[Non-Refundable ]]></PromotionDescription></SupplierPromotion></PriceInfo><PriceInfo><ItemNo>28</ItemNo><ItemCode>SEL0106</ItemCode><SupplierCompCode></SupplierCompCode><RoomTypeCode>20200411|20200414|W|435|111653|SUI.PE|ID_B2B_26|RO|ODCC25|3~1~0||N@04~~22c163e~-838227779~N~~B7C05C0C859941D157892533275902PAAR0000019001000060825012d5:EICB.IA:suite premier::A0#B0#C0#D0#E0|KHKPRJZM|~None</RoomTypeCode><RoomTypeName><![CDATA[suite premier]]></RoomTypeName><BreakfastTypeName><![CDATA[None]]></BreakfastTypeName><AddBreakfastTypeName></AddBreakfastTypeName><PriceComment><![CDATA[]]></PriceComment><FareRateType>None</FareRateType><PriceStatus>Available</PriceStatus><NetCurrencyCode>USD</NetCurrencyCode><NetConvertRate>1.00000000</NetConvertRate><SellerNetPrice>5159</SellerNetPrice><LocalNetPrice>5159.33</LocalNetPrice><SellerMarkupPrice>0</SellerMarkupPrice><RecommendClientPrice>5883</RecommendClientPrice><SellerClientPrice>5159</SellerClientPrice><Comment><![CDATA[]]></Comment><DoubleBedYn>false</DoubleBedYn></PriceInfo><PriceInfo><ItemNo>28</ItemNo><ItemCode>SEL0106</ItemCode><SupplierCompCode></SupplierCompCode><RoomTypeCode>20200411|20200414|W|435|111653|SUI.PE|ID_B2B_26|BB|ODBB25|3~1~0||N@04~~2251749~-1859799172~N~~B7C05C0C859941D157892533275902PAAR0000019001000060825313b7:FAEH.ID:suite premier::A0#B0#C0#D0#E0|KDFHRHGBH|~Breakfast</RoomTypeCode><RoomTypeName><![CDATA[suite premier]]></RoomTypeName><BreakfastTypeName><![CDATA[Breakfast]]></BreakfastTypeName><AddBreakfastTypeName></AddBreakfastTypeName><PriceComment><![CDATA[]]></PriceComment><FareRateType>None</FareRateType><PriceStatus>Available</PriceStatus><NetCurrencyCode>USD</NetCurrencyCode><NetConvertRate>1.00000000</NetConvertRate><SellerNetPrice>5401</SellerNetPrice><LocalNetPrice>5401.18</LocalNetPrice><SellerMarkupPrice>0</SellerMarkupPrice><RecommendClientPrice>6158</RecommendClientPrice><SellerClientPrice>5401</SellerClientPrice><Comment><![CDATA[]]></Comment><DoubleBedYn>false</DoubleBedYn></PriceInfo><PriceInfo><ItemNo>28</ItemNo><ItemCode>SEL0106</ItemCode><SupplierCompCode></SupplierCompCode><RoomTypeCode>20200411|20200414|W|435|111653|SUI.ST|ID_B2B_26|RO|ODAP18|3~1~0||N@04~~25b3a63~41037768~N~~B7C05C0C859941D157892533275902PAAR0000019001000060822a3371:BDBGJ.EC:suite standard nrf::A0#B0#C0#D0#E0|HDFPHRZGPD|~None</RoomTypeCode><RoomTypeName><![CDATA[suite standard nrf]]></RoomTypeName><BreakfastTypeName><![CDATA[None]]></BreakfastTypeName><AddBreakfastTypeName></AddBreakfastTypeName><PriceComment><![CDATA[]]></PriceComment><FareRateType>None</FareRateType><PriceStatus>Available</PriceStatus><NetCurrencyCode>USD</NetCurrencyCode><NetConvertRate>1.00000000</NetConvertRate><SellerNetPrice>14091</SellerNetPrice><LocalNetPrice>14091.28</LocalNetPrice><SellerMarkupPrice>0</SellerMarkupPrice><RecommendClientPrice>16067</RecommendClientPrice><SellerClientPrice>14091</SellerClientPrice><Comment><![CDATA[]]></Comment><DoubleBedYn>false</DoubleBedYn><SupplierPromotion><PromotionName><![CDATA[Non-Refundable ]]></PromotionName><PromotionDescription><![CDATA[Non-Refundable ]]></PromotionDescription></SupplierPromotion></PriceInfo><PriceInfo><ItemNo>28</ItemNo><ItemCode>SEL0106</ItemCode><SupplierCompCode></SupplierCompCode><RoomTypeCode>20200411|20200414|W|435|111653|SUI.ST|ID_B2B_26|BB|ODAB18|3~1~0||N@04~~256430f~-453849163~N~~B7C05C0C859941D157892533275902PAAR0000019001000060821c3b15:BFBCF.CI:suite standard nrf::A0#B0#C0#D0#E0|HMHBDRFDPM|~Breakfast</RoomTypeCode><RoomTypeName><![CDATA[suite standard nrf]]></RoomTypeName><BreakfastTypeName><![CDATA[Breakfast]]></BreakfastTypeName><AddBreakfastTypeName></AddBreakfastTypeName><PriceComment><![CDATA[]]></PriceComment><FareRateType>None</FareRateType><PriceStatus>Available</PriceStatus><NetCurrencyCode>USD</NetCurrencyCode><NetConvertRate>1.00000000</NetConvertRate><SellerNetPrice>16184</SellerNetPrice><LocalNetPrice>16184.05</LocalNetPrice><SellerMarkupPrice>0</SellerMarkupPrice><RecommendClientPrice>18453</RecommendClientPrice><SellerClientPrice>16184</SellerClientPrice><Comment><![CDATA[]]></Comment><DoubleBedYn>false</DoubleBedYn><SupplierPromotion><PromotionName><![CDATA[Non-Refundable ]]></PromotionName><PromotionDescription><![CDATA[Non-Refundable ]]></PromotionDescription></SupplierPromotion></PriceInfo><PriceInfo><ItemNo>28</ItemNo><ItemCode>SEL0106</ItemCode><SupplierCompCode></SupplierCompCode><RoomTypeCode>20200411|20200414|W|435|111653|SUI.ST|ID_B2B_26|RO|ODCC25|3~1~0||N@04~~2374dda~-459510610~N~~B7C05C0C859941D157892533275902PAAR0000019001000060822241ec:BGIHG.DE:suite standard::A0#B0#C0#D0#E0|HBFKGRMBJB|~None</RoomTypeCode><RoomTypeName><![CDATA[suite standard]]></RoomTypeName><BreakfastTypeName><![CDATA[None]]></BreakfastTypeName><AddBreakfastTypeName></AddBreakfastTypeName><PriceComment><![CDATA[]]></PriceComment><FareRateType>None</FareRateType><PriceStatus>Available</PriceStatus><NetCurrencyCode>USD</NetCurrencyCode><NetConvertRate>1.00000000</NetConvertRate><SellerNetPrice>18058</SellerNetPrice><LocalNetPrice>18057.68</LocalNetPrice><SellerMarkupPrice>0</SellerMarkupPrice><RecommendClientPrice>20589</RecommendClientPrice><SellerClientPrice>18058</SellerClientPrice><Comment><![CDATA[]]></Comment><DoubleBedYn>false</DoubleBedYn></PriceInfo><PriceInfo><ItemNo>28</ItemNo><ItemCode>SEL0106</ItemCode><SupplierCompCode></SupplierCompCode><RoomTypeCode>20200411|20200414|W|435|111653|SUI.ST|ID_B2B_26|BB|ODBB25|3~1~0||N@04~~2304ee5~2087442021~N~~B7C05C0C859941D157892533275902PAAR0000019001000060822442ce:BHBAC.DG:suite standard::A0#B0#C0#D0#E0|HBZPPRKZKZ|~Breakfast</RoomTypeCode><RoomTypeName><![CDATA[suite standard]]></RoomTypeName><BreakfastTypeName><![CDATA[Breakfast]]></BreakfastTypeName><AddBreakfastTypeName></AddBreakfastTypeName><PriceComment><![CDATA[]]></PriceComment><FareRateType>None</FareRateType><PriceStatus>Available</PriceStatus><NetCurrencyCode>USD</NetCurrencyCode><NetConvertRate>1.00000000</NetConvertRate><SellerNetPrice>18300</SellerNetPrice><LocalNetPrice>18299.53</LocalNetPrice><SellerMarkupPrice>0</SellerMarkupPrice><RecommendClientPrice>20865</RecommendClientPrice><SellerClientPrice>18300</SellerClientPrice><Comment><![CDATA[]]></Comment><DoubleBedYn>false</DoubleBedYn></PriceInfo></PriceList></HotelItemInfo><HotelItemInfo><ItemCode>SEL0122</ItemCode><ItemName><![CDATA[tria hotel]]></ItemName><StarRating>3</StarRating><RecommendYn>False</RecommendYn><ExpertReportYn>False</ExpertReportYn><FirstImageFileName></FirstImageFileName><HotelDescription><![CDATA[]]></HotelDescription><BackpackYn>False</BackpackYn><BusinessYn>False</BusinessYn><HoneymoonYn>False</HoneymoonYn><FairYn>False</FairYn><AirPackYn>False</AirPackYn><BookingCount>2</BookingCount><LocationList></LocationList><PriceList><PriceInfo><ItemNo>16</ItemNo><ItemCode>SEL0122</ItemCode><SupplierCompCode></SupplierCompCode><RoomTypeCode>230548|GAGRZA|GNRTN|Q|E|Standard Double|469ee2f3-8c57-0f61-73ef-be651cd3a98d|NONE|GBHRGKBP|~None</RoomTypeCode><RoomTypeName><![CDATA[Standard Double]]></RoomTypeName><BreakfastTypeName><![CDATA[None]]></BreakfastTypeName><AddBreakfastTypeName></AddBreakfastTypeName><PriceComment><![CDATA[]]></PriceComment><FareRateType>None</FareRateType><PriceStatus>Available</PriceStatus><NetCurrencyCode>USD</NetCurrencyCode><NetConvertRate>1.00000000</NetConvertRate><SellerNetPrice>782</SellerNetPrice><LocalNetPrice>781.76</LocalNetPrice><SellerMarkupPrice>0</SellerMarkupPrice><RecommendClientPrice>875</RecommendClientPrice><SellerClientPrice>782</SellerClientPrice><Comment><![CDATA[]]></Comment><DoubleBedYn>false</DoubleBedYn></PriceInfo><PriceInfo><ItemNo>16</ItemNo><ItemCode>SEL0122</ItemCode><SupplierCompCode></SupplierCompCode><RoomTypeCode>230548|GBQRDB|BTRGZ|Q|E|Royal Deluxe Double|58ed2af8-2f48-1dde-030f-d45ab998db7b|NONE|BKFRGZJZ|~None</RoomTypeCode><RoomTypeName><![CDATA[Royal Deluxe Double]]></RoomTypeName><BreakfastTypeName><![CDATA[None]]></BreakfastTypeName><AddBreakfastTypeName></AddBreakfastTypeName><PriceComment><![CDATA[]]></PriceComment><FareRateType>None</FareRateType><PriceStatus>Available</PriceStatus><NetCurrencyCode>USD</NetCurrencyCode><NetConvertRate>1.00000000</NetConvertRate><SellerNetPrice>851</SellerNetPrice><LocalNetPrice>850.72</LocalNetPrice><SellerMarkupPrice>0</SellerMarkupPrice><RecommendClientPrice>952</RecommendClientPrice><SellerClientPrice>851</SellerClientPrice><Comment><![CDATA[]]></Comment><DoubleBedYn>false</DoubleBedYn></PriceInfo></PriceList></HotelItemInfo><HotelItemInfo><ItemCode>SEL0126</ItemCode><ItemName><![CDATA[best western premier gang nam]]></ItemName><StarRating>4</StarRating><RecommendYn>False</RecommendYn><ExpertReportYn>False</ExpertReportYn><FirstImageFileName></FirstImageFileName><HotelDescription><![CDATA[]]></HotelDescription><BackpackYn>False</BackpackYn><BusinessYn>False</BusinessYn><HoneymoonYn>False</HoneymoonYn><FairYn>False</FairYn><AirPackYn>False</AirPackYn><BookingCount>1</BookingCount><GeoCode><Latitude>37.506432</Latitude><Longitude>127.029837</Longitude></GeoCode><LocationList></LocationList><PriceList><PriceInfo><ItemNo>25</ItemNo><ItemCode>SEL0126</ItemCode><SupplierCompCode></SupplierCompCode><RoomTypeCode>20200411|20200414|W|435|122318|ROO.1B|ID_B2B_57|RO|15D|3~1~0||N@04~~22a391~-374179948~N~~B7C05C0C859941D157892533275902PAAR0000019001000060820a345:IDH.BA:room one bed nrf::A0#B0#C0#D0#E0|BPKRMPG|~None</RoomTypeCode><RoomTypeName><![CDATA[room one bed nrf]]></RoomTypeName><BreakfastTypeName><![CDATA[None]]></BreakfastTypeName><AddBreakfastTypeName></AddBreakfastTypeName><PriceComment><![CDATA[]]></PriceComment><FareRateType>None</FareRateType><PriceStatus>Available</PriceStatus><NetCurrencyCode>USD</NetCurrencyCode><NetConvertRate>1.00000000</NetConvertRate><SellerNetPrice>896</SellerNetPrice><LocalNetPrice>895.70</LocalNetPrice><SellerMarkupPrice>0</SellerMarkupPrice><RecommendClientPrice>1021</RecommendClientPrice><SellerClientPrice>896</SellerClientPrice><Comment><![CDATA[]]></Comment><DoubleBedYn>false</DoubleBedYn><SupplierPromotion><PromotionName><![CDATA[Non-Refundable ]]></PromotionName><PromotionDescription><![CDATA[Non-Refundable ]]></PromotionDescription></SupplierPromotion></PriceInfo><PriceInfo><ItemNo>25</ItemNo><ItemCode>SEL0126</ItemCode><SupplierCompCode></SupplierCompCode><RoomTypeCode>20200411|20200414|W|435|122318|ROO.DB|ID_B2B_57|RO|15D|3~1~0||N@04~~20b3da~495964340~N~~B7C05C0C859941D157892533275902PAAR00000190010000608248387:JAD.HC:room with double bed nrf::A0#B0#C0#D0#E0|PMMRPBFD|~None</RoomTypeCode><RoomTypeName><![CDATA[room with double bed nrf]]></RoomTypeName><BreakfastTypeName><![CDATA[None]]></BreakfastTypeName><AddBreakfastTypeName></AddBreakfastTypeName><PriceComment><![CDATA[]]></PriceComment><FareRateType>None</FareRateType><PriceStatus>Available</PriceStatus><NetCurrencyCode>USD</NetCurrencyCode><NetConvertRate>1.00000000</NetConvertRate><SellerNetPrice>967</SellerNetPrice><LocalNetPrice>966.98</LocalNetPrice><SellerMarkupPrice>0</SellerMarkupPrice><RecommendClientPrice>1103</RecommendClientPrice><SellerClientPrice>967</SellerClientPrice><Comment><![CDATA[]]></Comment><DoubleBedYn>false</DoubleBedYn><SupplierPromotion><PromotionName><![CDATA[Non-Refundable ]]></PromotionName><PromotionDescription><![CDATA[Non-Refundable ]]></PromotionDescription></SupplierPromotion></PriceInfo><PriceInfo><ItemNo>25</ItemNo><ItemCode>SEL0126</ItemCode><SupplierCompCode></SupplierCompCode><RoomTypeCode>20200411|20200414|W|435|122318|ROO.2B|ID_B2B_57|RO|15D|3~1~0||N@04~~20b3da~-624655966~N~~B7C05C0C859941D157892533275902PAAR00000190010000608248387:JAD.HC:room two beds nrf::A0#B0#C0#D0#E0|PMMRPBFD|~None</RoomTypeCode><RoomTypeName><![CDATA[room two beds nrf]]></RoomTypeName><BreakfastTypeName><![CDATA[None]]></BreakfastTypeName><AddBreakfastTypeName></AddBreakfastTypeName><PriceComment><![CDATA[]]></PriceComment><FareRateType>None</FareRateType><PriceStatus>Available</PriceStatus><NetCurrencyCode>USD</NetCurrencyCode><NetConvertRate>1.00000000</NetConvertRate><SellerNetPrice>967</SellerNetPrice><LocalNetPrice>966.98</LocalNetPrice><SellerMarkupPrice>0</SellerMarkupPrice><RecommendClientPrice>1103</RecommendClientPrice><SellerClientPrice>967</SellerClientPrice><Comment><![CDATA[]]></Comment><DoubleBedYn>false</DoubleBedYn><SupplierPromotion><PromotionName><![CDATA[Non-Refundable ]]></PromotionName><PromotionDescription><![CDATA[Non-Refundable ]]></PromotionDescription></SupplierPromotion></PriceInfo><PriceInfo><ItemNo>25</ItemNo><ItemCode>SEL0126</ItemCode><SupplierCompCode></SupplierCompCode><RoomTypeCode>20200411|20200414|W|435|122318|ROO.1B|ID_B2B_57|RO|D2|3~1~0||P@04~~200451~-1649040635~N~~B7C05C0C859941D157892533275902PAAR00000190010000608200451:BBAF.AA:room one bed::A0#B0#C0#D0#E0|HHBZRJK|~None</RoomTypeCode><RoomTypeName><![CDATA[room one bed]]></RoomTypeName><BreakfastTypeName><![CDATA[None]]></BreakfastTypeName><AddBreakfastTypeName></AddBreakfastTypeName><PriceComment><![CDATA[]]></PriceComment><FareRateType>None</FareRateType><PriceStatus>Available</PriceStatus><NetCurrencyCode>USD</NetCurrencyCode><NetConvertRate>1.00000000</NetConvertRate><SellerNetPrice>1182</SellerNetPrice><LocalNetPrice>1182.35</LocalNetPrice><SellerMarkupPrice>0</SellerMarkupPrice><RecommendClientPrice>1348</RecommendClientPrice><SellerClientPrice>1182</SellerClientPrice><Comment><![CDATA[]]></Comment><DoubleBedYn>false</DoubleBedYn></PriceInfo><PriceInfo><ItemNo>25</ItemNo><ItemCode>SEL0126</ItemCode><SupplierCompCode></SupplierCompCode><RoomTypeCode>20200411|20200414|W|435|122318|ROO.DB|ID_B2B_57|RO|D2|3~1~0||P@04~~25c4a8~610165996~N~~B7C05C0C859941D157892533275902PAAR0000019001000060825c4a8:BBJC.JC:room with double bed::A0#B0#C0#D0#E0|HZGMRDZDD|~None</RoomTypeCode><RoomTypeName><![CDATA[room with double bed]]></RoomTypeName><BreakfastTypeName><![CDATA[None]]></BreakfastTypeName><AddBreakfastTypeName></AddBreakfastTypeName><PriceComment><![CDATA[]]></PriceComment><FareRateType>None</FareRateType><PriceStatus>Available</PriceStatus><NetCurrencyCode>USD</NetCurrencyCode><NetConvertRate>1.00000000</NetConvertRate><SellerNetPrice>1276</SellerNetPrice><LocalNetPrice>1276.42</LocalNetPrice><SellerMarkupPrice>0</SellerMarkupPrice><RecommendClientPrice>1455</RecommendClientPrice><SellerClientPrice>1276</SellerClientPrice><Comment><![CDATA[]]></Comment><DoubleBedYn>false</DoubleBedYn></PriceInfo><PriceInfo><ItemNo>25</ItemNo><ItemCode>SEL0126</ItemCode><SupplierCompCode></SupplierCompCode><RoomTypeCode>20200411|20200414|W|435|122318|ROO.2B|ID_B2B_57|RO|D2|3~1~0||P@04~~25c4a8~712564286~N~~B7C05C0C859941D157892533275902PAAR0000019001000060825c4a8:BBJC.JC:room two beds::A0#B0#C0#D0#E0|HZGMRDZDD|~None</RoomTypeCode><RoomTypeName><![CDATA[room two beds]]></RoomTypeName><BreakfastTypeName><![CDATA[None]]></BreakfastTypeName><AddBreakfastTypeName></AddBreakfastTypeName><PriceComment><![CDATA[]]></PriceComment><FareRateType>None</FareRateType><PriceStatus>Available</PriceStatus><NetCurrencyCode>USD</NetCurrencyCode><NetConvertRate>1.00000000</NetConvertRate><SellerNetPrice>1276</SellerNetPrice><LocalNetPrice>1276.42</LocalNetPrice><SellerMarkupPrice>0</SellerMarkupPrice><RecommendClientPrice>1455</RecommendClientPrice><SellerClientPrice>1276</SellerClientPrice><Comment><![CDATA[]]></Comment><DoubleBedYn>false</DoubleBedYn></PriceInfo><PriceInfo><ItemNo>25</ItemNo><ItemCode>SEL0126</ItemCode><SupplierCompCode></SupplierCompCode><RoomTypeCode>20200411|20200414|W|435|122318|JSU.KG|ID_B2B_57|RO|15D|3~1~0||N@04~~22a5f6~1106044108~N~~B7C05C0C859941D157892533275902PAAR00000190010000608257576:BDJI.IH:junior suite king size bed nrf::A0#B0#C0#D0#E0|HDPMRGPFP|~None</RoomTypeCode><RoomTypeName><![CDATA[junior suite king size bed nrf]]></RoomTypeName><BreakfastTypeName><![CDATA[None]]></BreakfastTypeName><AddBreakfastTypeName></AddBreakfastTypeName><PriceComment><![CDATA[]]></PriceComment><FareRateType>None</FareRateType><PriceStatus>Available</PriceStatus><NetCurrencyCode>USD</NetCurrencyCode><NetConvertRate>1.00000000</NetConvertRate><SellerNetPrice>1497</SellerNetPrice><LocalNetPrice>1496.79</LocalNetPrice><SellerMarkupPrice>0</SellerMarkupPrice><RecommendClientPrice>1707</RecommendClientPrice><SellerClientPrice>1497</SellerClientPrice><Comment><![CDATA[]]></Comment><DoubleBedYn>false</DoubleBedYn><SupplierPromotion><PromotionName><![CDATA[Non-Refundable ]]></PromotionName><PromotionDescription><![CDATA[Non-Refundable ]]></PromotionDescription></SupplierPromotion></PriceInfo><PriceInfo><ItemNo>25</ItemNo><ItemCode>SEL0126</ItemCode><SupplierCompCode></SupplierCompCode><RoomTypeCode>20200411|20200414|W|435|122318|JSU.KG|ID_B2B_57|RO|D2|3~1~0||P@04~~237736~-1824540926~N~~B7C05C0C859941D157892533275902PAAR00000190010000608237736:BIEG.FF:junior suite king size bed::A0#B0#C0#D0#E0|HPGKRBFBK|~None</RoomTypeCode><RoomTypeName><![CDATA[junior suite king size bed]]></RoomTypeName><BreakfastTypeName><![CDATA[None]]></BreakfastTypeName><AddBreakfastTypeName></AddBreakfastTypeName><PriceComment><![CDATA[]]></PriceComment><FareRateType>None</FareRateType><PriceStatus>Available</PriceStatus><NetCurrencyCode>USD</NetCurrencyCode><NetConvertRate>1.00000000</NetConvertRate><SellerNetPrice>1976</SellerNetPrice><LocalNetPrice>1975.81</LocalNetPrice><SellerMarkupPrice>0</SellerMarkupPrice><RecommendClientPrice>2253</RecommendClientPrice><SellerClientPrice>1976</SellerClientPrice><Comment><![CDATA[]]></Comment><DoubleBedYn>false</DoubleBedYn></PriceInfo></PriceList></HotelItemInfo><HotelItemInfo><ItemCode>SEL0137</ItemCode><ItemName><![CDATA[lotte city hotel]]></ItemName><StarRating>4</StarRating><RecommendYn>False</RecommendYn><ExpertReportYn>False</ExpertReportYn><FirstImageFileName></FirstImageFileName><HotelDescription><![CDATA[]]></HotelDescription><BackpackYn>False</BackpackYn><BusinessYn>False</BusinessYn><HoneymoonYn>False</HoneymoonYn><FairYn>False</FairYn><AirPackYn>False</AirPackYn><BookingCount>2</BookingCount><GeoCode><Latitude>37.536664</Latitude><Longitude>126.944031</Longitude></GeoCode><LocationList></LocationList><PriceList><PriceInfo><ItemNo>23</ItemNo><ItemCode>SEL0137</ItemCode><SupplierCompCode></SupplierCompCode><RoomTypeCode>154786|AQQARQG|AAARZE|Q|E|Standard Double Room|f0b7eb30-3fb3-ed98-2144-f687fe00acb9|NONE|HFPHRHMMJ|~None</RoomTypeCode><RoomTypeName><![CDATA[Standard Double Room]]></RoomTypeName><BreakfastTypeName><![CDATA[None]]></BreakfastTypeName><AddBreakfastTypeName></AddBreakfastTypeName><PriceComment><![CDATA[]]></PriceComment><FareRateType>None</FareRateType><PriceStatus>Available</PriceStatus><NetCurrencyCode>USD</NetCurrencyCode><NetConvertRate>1.00000000</NetConvertRate><SellerNetPrice>1091</SellerNetPrice><LocalNetPrice>1091.17</LocalNetPrice><SellerMarkupPrice>0</SellerMarkupPrice><RecommendClientPrice>1221</RecommendClientPrice><SellerClientPrice>1091</SellerClientPrice><Comment><![CDATA[]]></Comment><DoubleBedYn>false</DoubleBedYn><SupplierPromotion><PromotionName><![CDATA[Early Booking Saver. Price includes 15% discount!]]></PromotionName><PromotionDescription><![CDATA[]]></PromotionDescription></SupplierPromotion></PriceInfo><PriceInfo><ItemNo>23</ItemNo><ItemCode>SEL0137</ItemCode><SupplierCompCode></SupplierCompCode><RoomTypeCode>154786|AQAGRAB|AAERQZ|Q|E|Deluxe Twin Room|5ccb0c1b-4479-2f2e-1ed6-1114c0208215|NONE|HHFBRGZMZ|~None</RoomTypeCode><RoomTypeName><![CDATA[Deluxe Twin Room]]></RoomTypeName><BreakfastTypeName><![CDATA[None]]></BreakfastTypeName><AddBreakfastTypeName></AddBreakfastTypeName><PriceComment><![CDATA[]]></PriceComment><FareRateType>None</FareRateType><PriceStatus>Available</PriceStatus><NetCurrencyCode>USD</NetCurrencyCode><NetConvertRate>1.00000000</NetConvertRate><SellerNetPrice>1109</SellerNetPrice><LocalNetPrice>1108.73</LocalNetPrice><SellerMarkupPrice>0</SellerMarkupPrice><RecommendClientPrice>1241</RecommendClientPrice><SellerClientPrice>1109</SellerClientPrice><Comment><![CDATA[]]></Comment><DoubleBedYn>false</DoubleBedYn><SupplierPromotion><PromotionName><![CDATA[Early Booking Saver. Price includes 15% discount!]]></PromotionName><PromotionDescription><![CDATA[]]></PromotionDescription></SupplierPromotion></PriceInfo><PriceInfo><ItemNo>23</ItemNo><ItemCode>SEL0137</ItemCode><SupplierCompCode></SupplierCompCode><RoomTypeCode>154786|AQTCRTQ|AABRDQ|Q|E|Superior Double City View|abfeb654-fd80-d9a6-03b0-d6dcc3275e15|NONE|HHMHRKFD|~None</RoomTypeCode><RoomTypeName><![CDATA[Superior Double City View]]></RoomTypeName><BreakfastTypeName><![CDATA[None]]></BreakfastTypeName><AddBreakfastTypeName></AddBreakfastTypeName><PriceComment><![CDATA[]]></PriceComment><FareRateType>None</FareRateType><PriceStatus>Available</PriceStatus><NetCurrencyCode>USD</NetCurrencyCode><NetConvertRate>1.00000000</NetConvertRate><SellerNetPrice>1162</SellerNetPrice><LocalNetPrice>1161.50</LocalNetPrice><SellerMarkupPrice>0</SellerMarkupPrice><RecommendClientPrice>1300</RecommendClientPrice><SellerClientPrice>1162</SellerClientPrice><Comment><![CDATA[]]></Comment><DoubleBedYn>false</DoubleBedYn><SupplierPromotion><PromotionName><![CDATA[Early Booking Saver. Price includes 15% discount!]]></PromotionName><PromotionDescription><![CDATA[]]></PromotionDescription></SupplierPromotion></PriceInfo><PriceInfo><ItemNo>23</ItemNo><ItemCode>SEL0137</ItemCode><SupplierCompCode></SupplierCompCode><RoomTypeCode>154786|AQGCREZ|AANRDB|Q|E|Deluxe Family Twin Room|1c47efa7-f1cc-e05c-28fc-4451b2933be6|NONE|HHGZRFPBB|~None</RoomTypeCode><RoomTypeName><![CDATA[Deluxe Family Twin Room]]></RoomTypeName><BreakfastTypeName><![CDATA[None]]></BreakfastTypeName><AddBreakfastTypeName></AddBreakfastTypeName><PriceComment><![CDATA[]]></PriceComment><FareRateType>None</FareRateType><PriceStatus>Available</PriceStatus><NetCurrencyCode>USD</NetCurrencyCode><NetConvertRate>1.00000000</NetConvertRate><SellerNetPrice>1172</SellerNetPrice><LocalNetPrice>1172.10</LocalNetPrice><SellerMarkupPrice>0</SellerMarkupPrice><RecommendClientPrice>1312</RecommendClientPrice><SellerClientPrice>1172</SellerClientPrice><Comment><![CDATA[]]></Comment><DoubleBedYn>false</DoubleBedYn><SupplierPromotion><PromotionName><![CDATA[Early Booking Saver. Price includes 15% discount!]]></PromotionName><PromotionDescription><![CDATA[]]></PromotionDescription></SupplierPromotion></PriceInfo><PriceInfo><ItemNo>23</ItemNo><ItemCode>SEL0137</ItemCode><SupplierCompCode></SupplierCompCode><RoomTypeCode>154786|AZNBRAT|ADDRZD|Q|E|Standard Double Room|15641f18-eedd-0a35-f95f-ef3fdd3af80c|NONE|HDHDRPPDD|~Breakfast for 2 persons</RoomTypeCode><RoomTypeName><![CDATA[Standard Double Room]]></RoomTypeName><BreakfastTypeName><![CDATA[Breakfast for 2 persons]]></BreakfastTypeName><AddBreakfastTypeName></AddBreakfastTypeName><PriceComment><![CDATA[]]></PriceComment><FareRateType>None</FareRateType><PriceStatus>Available</PriceStatus><NetCurrencyCode>USD</NetCurrencyCode><NetConvertRate>1.00000000</NetConvertRate><SellerNetPrice>1415</SellerNetPrice><LocalNetPrice>1414.99</LocalNetPrice><SellerMarkupPrice>0</SellerMarkupPrice><RecommendClientPrice>1584</RecommendClientPrice><SellerClientPrice>1415</SellerClientPrice><Comment><![CDATA[]]></Comment><DoubleBedYn>false</DoubleBedYn><SupplierPromotion><PromotionName><![CDATA[Early Booking Saver. Price includes 15% discount!]]></PromotionName><PromotionDescription><![CDATA[]]></PromotionDescription></SupplierPromotion></PriceInfo><PriceInfo><ItemNo>23</ItemNo><ItemCode>SEL0137</ItemCode><SupplierCompCode></SupplierCompCode><RoomTypeCode>154786|AECZRDE|ACQRZG|Q|E|Standard Double|dca92b5f-3291-99e5-ff18-fc3f5837ad8d|NONE|HDGDRHDBG|~Breakfast for 1 person</RoomTypeCode><RoomTypeName><![CDATA[Standard Double]]></RoomTypeName><BreakfastTypeName><![CDATA[Breakfast for 1 person]]></BreakfastTypeName><AddBreakfastTypeName></AddBreakfastTypeName><PriceComment><![CDATA[]]></PriceComment><FareRateType>None</FareRateType><PriceStatus>Available</PriceStatus><NetCurrencyCode>USD</NetCurrencyCode><NetConvertRate>1.00000000</NetConvertRate><SellerNetPrice>1474</SellerNetPrice><LocalNetPrice>1474.15</LocalNetPrice><SellerMarkupPrice>0</SellerMarkupPrice><RecommendClientPrice>1650</RecommendClientPrice><SellerClientPrice>1474</SellerClientPrice><Comment><![CDATA[]]></Comment><DoubleBedYn>false</DoubleBedYn></PriceInfo><PriceInfo><ItemNo>23</ItemNo><ItemCode>SEL0137</ItemCode><SupplierCompCode></SupplierCompCode><RoomTypeCode>154786|AETZRTN|ACARDA|Q|E|Superior Double City View|d0374cd4-bce5-1fc9-e5d9-5abf9655db1f|NONE|HDBKRJJZH|~Breakfast for 2 persons</RoomTypeCode><RoomTypeName><![CDATA[Superior Double City View]]></RoomTypeName><BreakfastTypeName><![CDATA[Breakfast for 2 persons]]></BreakfastTypeName><AddBreakfastTypeName></AddBreakfastTypeName><PriceComment><![CDATA[]]></PriceComment><FareRateType>None</FareRateType><PriceStatus>Available</PriceStatus><NetCurrencyCode>USD</NetCurrencyCode><NetConvertRate>1.00000000</NetConvertRate><SellerNetPrice>1485</SellerNetPrice><LocalNetPrice>1485.33</LocalNetPrice><SellerMarkupPrice>0</SellerMarkupPrice><RecommendClientPrice>1662</RecommendClientPrice><SellerClientPrice>1485</SellerClientPrice><Comment><![CDATA[]]></Comment><DoubleBedYn>false</DoubleBedYn><SupplierPromotion><PromotionName><![CDATA[Early Booking Saver. Price includes 15% discount!]]></PromotionName><PromotionDescription><![CDATA[]]></PromotionDescription></SupplierPromotion></PriceInfo><PriceInfo><ItemNo>23</ItemNo><ItemCode>SEL0137</ItemCode><SupplierCompCode></SupplierCompCode><RoomTypeCode>154786|ADZGREA|ACBRCN|Q|E|Deluxe Twin Room|30e6dff3-2eb6-9f19-6019-b09a40a2ca55|NONE|HKKKRGMGP|~Breakfast for 2 persons</RoomTypeCode><RoomTypeName><![CDATA[Deluxe Twin Room]]></RoomTypeName><BreakfastTypeName><![CDATA[Breakfast for 2 persons]]></BreakfastTypeName><AddBreakfastTypeName></AddBreakfastTypeName><PriceComment><![CDATA[]]></PriceComment><FareRateType>None</FareRateType><PriceStatus>Available</PriceStatus><NetCurrencyCode>USD</NetCurrencyCode><NetConvertRate>1.00000000</NetConvertRate><SellerNetPrice>1556</SellerNetPrice><LocalNetPrice>1555.77</LocalNetPrice><SellerMarkupPrice>0</SellerMarkupPrice><RecommendClientPrice>1741</RecommendClientPrice><SellerClientPrice>1556</SellerClientPrice><Comment><![CDATA[]]></Comment><DoubleBedYn>false</DoubleBedYn><SupplierPromotion><PromotionName><![CDATA[Early Booking Saver. Price includes 15% discount!]]></PromotionName><PromotionDescription><![CDATA[]]></PromotionDescription></SupplierPromotion></PriceInfo></PriceList></HotelItemInfo><HotelItemInfo><ItemCode>SEL0192</ItemCode><ItemName><![CDATA[hotel irene]]></ItemName><StarRating>2+</StarRating><RecommendYn>False</RecommendYn><ExpertReportYn>False</ExpertReportYn><FirstImageFileName></FirstImageFileName><HotelDescription><![CDATA[]]></HotelDescription><BackpackYn>False</BackpackYn><BusinessYn>False</BusinessYn><HoneymoonYn>False</HoneymoonYn><FairYn>False</FairYn><AirPackYn>False</AirPackYn><BookingCount>1</BookingCount><GeoCode><Latitude>37.562813</Latitude><Longitude>126.977735</Longitude></GeoCode><LocationList></LocationList><PriceList><PriceInfo><ItemNo>27</ItemNo><ItemCode>SEL0192</ItemCode><SupplierCompCode></SupplierCompCode><RoomTypeCode>247805|TAEREC|TBRAC|Q|E|Standard Twin|6093e894-2b1f-2120-c87c-2eacc9280f35|NONE|MMBRKKHK|~None</RoomTypeCode><RoomTypeName><![CDATA[Standard Twin]]></RoomTypeName><BreakfastTypeName><![CDATA[None]]></BreakfastTypeName><AddBreakfastTypeName></AddBreakfastTypeName><PriceComment><![CDATA[]]></PriceComment><FareRateType>None</FareRateType><PriceStatus>Available</PriceStatus><NetCurrencyCode>USD</NetCurrencyCode><NetConvertRate>1.00000000</NetConvertRate><SellerNetPrice>669</SellerNetPrice><LocalNetPrice>668.55</LocalNetPrice><SellerMarkupPrice>0</SellerMarkupPrice><RecommendClientPrice>748</RecommendClientPrice><SellerClientPrice>669</SellerClientPrice><Comment><![CDATA[]]></Comment><DoubleBedYn>false</DoubleBedYn></PriceInfo><PriceInfo><ItemNo>27</ItemNo><ItemCode>SEL0192</ItemCode><SupplierCompCode></SupplierCompCode><RoomTypeCode>247805|GCTRET|BDRQD|Q|E|Suite|3045f512-bf66-5545-83b3-2f5c20fafbc2|NONE|BZDRDJZD|~None</RoomTypeCode><RoomTypeName><![CDATA[Suite]]></RoomTypeName><BreakfastTypeName><![CDATA[None]]></BreakfastTypeName><AddBreakfastTypeName></AddBreakfastTypeName><PriceComment><![CDATA[]]></PriceComment><FareRateType>None</FareRateType><PriceStatus>Available</PriceStatus><NetCurrencyCode>USD</NetCurrencyCode><NetConvertRate>1.00000000</NetConvertRate><SellerNetPrice>824</SellerNetPrice><LocalNetPrice>824.43</LocalNetPrice><SellerMarkupPrice>0</SellerMarkupPrice><RecommendClientPrice>923</RecommendClientPrice><SellerClientPrice>824</SellerClientPrice><Comment><![CDATA[]]></Comment><DoubleBedYn>false</DoubleBedYn></PriceInfo></PriceList></HotelItemInfo></HotelSearchList><Errors></Errors></GetHotelSearchListResult></GetHotelSearchListResponse></GetHotelSearchListForCustomerCountResult></GetHotelSearchListForCustomerCountResponse></soap:Body></soap:Envelope>